{"result":"ok","value":{"more_pics":true,"last_pic_id":11092607,"pic_count":240,"pics":[{"view_count":4,"creator":{"username":"daidai634","display_name":"daidai634","following_count":570,"follower_count":734,"id":676490,"icon":{"url":"http://s1.ui1.picplzthumbs.com/usericons/36/ea/b0/36eab0d63e1c24c1af8f654fd041807ed85c1449_meds.jpg","width":75,"height":75}},"url":"/user/daidai634/pic/1xpd6/","pic_files":{"640r":{"width":640,"img_url":"http://s2.i1.picplzthumbs.com/upload/img/1a/a1/a6/1aa1a6d967b3bd1d8127c08cfcd8a9fe9fe82da1_wmeg.jpg","height":640},"100sh":{"width":100,"img_url":"http://s2.i1.picplzthumbs.com/upload/img/1a/a1/a6/1aa1a6d967b3bd1d8127c08cfcd8a9fe9fe82da1_t200s.jpg","height":100},"320rh":{"width":320,"img_url":"http://s2.i1.picplzthumbs.com/upload/img/1a/a1/a6/1aa1a6d967b3bd1d8127c08cfcd8a9fe9fe82da1_mmed.jpg","height":320}},"caption":"\u306a\u3093\u304b\u3061\u3087\u3063\u3068\u30b8\u30d6\u30ea\u3063\u307d\u3044\u306a\u3068\u3002","comment_count":0,"like_count":9,"date":1338080747,"id":11097602},{"view_count":25,"creator":{"username":"foofighters41","display_name":"foofighters42","following_count":512,"follower_count":362,"id":1117352,"icon":{"url":"http://s0.ui1.picplzthumbs.com/usericons/2a/d2/8b/2ad28b85fc954d7802758b5279fc767d47398504_meds.jpg","width":75,"height":75}},"url":"/user/foofighters41/pic/1dw13/","pic_files":{"640r":{"width":640,"img_url":"http://s2.i1.picplzthumbs.com/upload/img/99/08/7d/99087db1f84154708b6bc45eab05f9955c038b9f_wmeg.jpg","height":474},"100sh":{"width":100,"img_url":"http://s2.i1.picplzthumbs.com/upload/img/99/08/7d/99087db1f84154708b6bc45eab05f9955c038b9f_t200s.jpg","height":100},"320rh":{"width":320,"img_url":"http://s2.i1.picplzthumbs.com/upload/img/99/08/7d/99087db1f84154708b6bc45eab05f9955c038b9f_mmed.jpg","height":237}},"caption":"\u3072\u3064\u3058\u3055\u3093\uff01\u5fae\u5999\u306b\u30ef\u30a4\u30eb\u30c9\u3060\u305c\u3047\uff5e(\u00b4\u0434\uff40)","comment_count":8,"like_count":16,"date":1338075975,"id":11096498},{"view_count":2,"creator":{"username":"cookieraider","display_name":"Maria","following_count":1805,"follower_count":749,"id":1488282,"icon":{"url":"http://s2.ui1.picplzthumbs.com/usericons/b6/bf/7a/b6bf7a91bb10aae6b70cea7472caa9f698328e79_meds.jpg","width":75,"height":75}},"url":"/user/cookieraider/pic/1xpc2/","pic_files":{"640r":{"width":476,"img_url":"http://s2.i1.picplzthumbs.com/upload/img/e6/77/01/e67701ace16b87d0dc4ced7b4c50d6044099270a_wmeg.jpg","height":640},"100sh":{"width":100,"img_url":"http://s2.i1.picplzthumbs.com/upload/img/e6/77/01/e67701ace16b87d0dc4ced7b4c50d6044099270a_t200s.jpg","height":100},"320rh":{"width":238,"img_url":"http://s2.i1.picplzthumbs.com/upload/img/e6/77/01/e67701ace16b87d0dc4ced7b4c50d6044099270a_mmed.jpg","height":320}},"caption":"8)","comment_count":0,"like_count":10,"date":1338080340,"id":11097494},{"view_count":5,"creator":{"username":"daidai634","display_name":"daidai634","following_count":570,"follower_count":734,"id":676490,"icon":{"url":"http://s1.ui1.picplzthumbs.com/usericons/36/ea/b0/36eab0d63e1c24c1af8f654fd041807ed85c1449_meds.jpg","width":75,"height":75}},"url":"/user/daidai634/pic/1xpxh/","pic_files":{"640r":{"width":640,"img_url":"http://s1.i1.picplzthumbs.com/upload/img/0d/6e/86/0d6e868b959316ab3f30d4781e7ee74c46c8ac29_wmeg.jpg","height":480},"100sh":{"width":100,"img_url":"http://s1.i1.picplzthumbs.com/upload/img/0d/6e/86/0d6e868b959316ab3f30d4781e7ee74c46c8ac29_t200s.jpg","height":100},"320rh":{"width":320,"img_url":"http://s1.i1.picplzthumbs.com/upload/img/0d/6e/86/0d6e868b959316ab3f30d4781e7ee74c46c8ac29_mmed.jpg","height":240}},"caption":"\u5973\u306e\u5b50\u305f\u3061\u306e\u5927\u96c6\u5408\uff01","comment_count":0,"like_count":8,"date":1338080917,"id":11097634},{"city":{"url":"/city/chiba-city-wakaba-ward-jp/","id":20936,"name":"Chiba City Wakaba Ward, Japan"},"creator":{"username":"nenagaraneru","display_name":"\u571f\u3044\u3058\u308a","following_count":1067,"follower_count":605,"id":1004425,"icon":{"url":"http://s1.ui1.picplzthumbs.com/usericons/8d/9e/87/8d9e8731b3fc2fdbcc58057d52565427e2ade5d6_meds.jpg","width":75,"height":75}},"url":"/user/nenagaraneru/pic/1xp4h/","pic_files":{"640r":{"width":480,"img_url":"http://s1.i1.picplzthumbs.com/upload/img/ac/8b/19/ac8b1997f56f96d02a294ec7ac743972166b3c2f_wmeg_00001.jpg","height":640},"100sh":{"width":100,"img_url":"http://s1.i1.picplzthumbs.com/upload/img/ac/8b/19/ac8b1997f56f96d02a294ec7ac743972166b3c2f_t200s_00001.jpg","height":100},"320rh":{"width":240,"img_url":"http://s1.i1.picplzthumbs.com/upload/img/ac/8b/19/ac8b1997f56f96d02a294ec7ac743972166b3c2f_mmed_00001.jpg","height":320}},"view_count":0,"caption":"\u81ea\u8ee2\u8eca\u4fee\u7406\u306b\u884c\u3053\u3046(^\u2227^)","comment_count":1,"like_count":8,"date":1338081432,"id":11097754},{"view_count":5,"creator":{"username":"eddie1856","display_name":"Eddie jacob","following_count":7014,"follower_count":8798,"id":304123,"icon":{"url":"http://s0.ui1.picplzthumbs.com/usericons/59/aa/5a/59aa5a54ce7a570ae86730b5e0a85c3fcd831518_meds.jpg","width":75,"height":75}},"url":"/user/eddie1856/pic/1dwkg/","pic_files":{"640r":{"width":640,"img_url":"http://s0.i1.picplzthumbs.com/upload/img/96/cd/71/96cd716a3b81473f67f9541ba23c7a8a97962731_wmeg_00001.jpg","height":391},"100sh":{"width":100,"img_url":"http://s0.i1.picplzthumbs.com/upload/img/96/cd/71/96cd716a3b81473f67f9541ba23c7a8a97962731_t200s_00001.jpg","height":100},"320rh":{"width":320,"img_url":"http://s0.i1.picplzthumbs.com/upload/img/96/cd/71/96cd716a3b81473f67f9541ba23c7a8a97962731_mmed_00001.jpg","height":195}},"caption":"Morning","comment_count":1,"like_count":27,"date":1338075316,"id":11096373},{"view_count":16,"creator":{"username":"26262626","display_name":"\u98a8\u5442","following_count":97,"follower_count":603,"id":757683,"icon":{"url":"http://s2.ui1.picplzthumbs.com/usericons/2c/a0/21/2ca021f1ca25c371996d4f55b434771f5adb144a_meds.jpg","width":75,"height":75}},"url":"/user/26262626/pic/1xp8p/","pic_files":{"640r":{"width":384,"img_url":"http://s0.i1.picplzthumbs.com/upload/img/24/9e/38/249e3811a3988b488c81c6456cf524cf29c7dbcc_wmeg.jpg","height":640},"100sh":{"width":100,"img_url":"http://s0.i1.picplzthumbs.com/upload/img/24/9e/38/249e3811a3988b488c81c6456cf524cf29c7dbcc_t200s.jpg","height":100},"320rh":{"width":192,"img_url":"http://s0.i1.picplzthumbs.com/upload/img/24/9e/38/249e3811a3988b488c81c6456cf524cf29c7dbcc_mmed.jpg","height":320}},"caption":"\u4ee5\u5fc3\u4f1d\u5fc3","comment_count":0,"like_count":8,"date":1338081012,"id":11097660},{"view_count":16,"creator":{"username":"foofighters41","display_name":"foofighters42","following_count":512,"follower_count":362,"id":1117352,"icon":{"url":"http://s0.ui1.picplzthumbs.com/usericons/2a/d2/8b/2ad28b85fc954d7802758b5279fc767d47398504_meds.jpg","width":75,"height":75}},"url":"/user/foofighters41/pic/1dsz0/","pic_files":{"640r":{"width":640,"img_url":"http://s0.i1.picplzthumbs.com/upload/img/a1/09/88/a109881305e49e5fc76eeba1074f15078b34fa35_wmeg.jpg","height":481},"100sh":{"width":100,"img_url":"http://s0.i1.picplzthumbs.com/upload/img/a1/09/88/a109881305e49e5fc76eeba1074f15078b34fa35_t200s.jpg","height":100},"320rh":{"width":320,"img_url":"http://s0.i1.picplzthumbs.com/upload/img/a1/09/88/a109881305e49e5fc76eeba1074f15078b34fa35_mmed.jpg","height":240}},"caption":"","comment_count":0,"like_count":22,"date":1338073317,"id":11096022},{"view_count":18,"creator":{"username":"gotenba","display_name":"suruga","following_count":2108,"follower_count":6837,"id":232354,"icon":{"url":"http://s1.ui1.picplzthumbs.com/usericons/47/77/4a/47774a177d4ad9a37fd9d292f20df9fbff509b4a_meds.jpg","width":75,"height":75}},"url":"/user/gotenba/pic/1xph8/","pic_files":{"640r":{"width":478,"img_url":"http://s1.i1.picplzthumbs.com/upload/img/9f/43/1a/9f431a90b0990776b57a416570b1476bc61decaf_wmeg.jpg","height":640},"100sh":{"width":100,"img_url":"http://s1.i1.picplzthumbs.com/upload/img/9f/43/1a/9f431a90b0990776b57a416570b1476bc61decaf_t200s.jpg","height":100},"320rh":{"width":239,"img_url":"http://s1.i1.picplzthumbs.com/upload/img/9f/43/1a/9f431a90b0990776b57a416570b1476bc61decaf_mmed.jpg","height":320}},"caption":"\u4e00\u6bb5\u4e0a\u3078(^-^)/","comment_count":0,"like_count":14,"date":1338078848,"id":11097142},{"view_count":0,"creator":{"username":"shainamp1093","display_name":"\"We are the Light...\"","following_count":174,"follower_count":112,"id":1388892,"icon":{"url":"http://s0.ui1.picplzthumbs.com/usericons/9a/d4/9d/9ad49d5bffff0047f3b6ffa6004a5f2ca11aec5f_meds.jpg","width":75,"height":75}},"url":"/user/shainamp1093/pic/1xpc5/","pic_files":{"640r":{"width":640,"img_url":"http://s2.i1.picplzthumbs.com/upload/img/36/5b/bd/365bbdb94e452bdded030688044e5c25ce0f36e8_wmeg.jpg","height":480},"100sh":{"width":100,"img_url":"http://s2.i1.picplzthumbs.com/upload/img/36/5b/bd/365bbdb94e452bdded030688044e5c25ce0f36e8_t200s.jpg","height":100},"320rh":{"width":320,"img_url":"http://s2.i1.picplzthumbs.com/upload/img/36/5b/bd/365bbdb94e452bdded030688044e5c25ce0f36e8_mmed.jpg","height":240}},"caption":"Twas a marvelous day :)","comment_count":0,"like_count":6,"date":1338080360,"id":11097503},{"view_count":21,"creator":{"username":"gotenba","display_name":"suruga","following_count":2108,"follower_count":6837,"id":232354,"icon":{"url":"http://s1.ui1.picplzthumbs.com/usericons/47/77/4a/47774a177d4ad9a37fd9d292f20df9fbff509b4a_meds.jpg","width":75,"height":75}},"url":"/user/gotenba/pic/1dw9t/","pic_files":{"640r":{"width":640,"img_url":"http://s2.i1.picplzthumbs.com/upload/img/66/ab/52/66ab5207264898f1b09fffbc78f5f0a755fad601_wmeg.jpg","height":426},"100sh":{"width":100,"img_url":"http://s2.i1.picplzthumbs.com/upload/img/66/ab/52/66ab5207264898f1b09fffbc78f5f0a755fad601_t200s.jpg","height":100},"320rh":{"width":320,"img_url":"http://s2.i1.picplzthumbs.com/upload/img/66/ab/52/66ab5207264898f1b09fffbc78f5f0a755fad601_mmed.jpg","height":213}},"caption":"\u4eca\u671d\u306e\u5bcc\u58eb\u5c71 (^-^)/ \u971e\u3093\u3067\u308b\u3002","comment_count":2,"like_count":21,"date":1338075479,"id":11096405},{"view_count":7,"creator":{"username":"juliwolke","display_name":"Lila","following_count":558,"follower_count":1389,"id":967188,"icon":{"url":"http://s2.ui1.picplzthumbs.com/usericons/03/5a/c4/035ac4ecec13515383c64851105c192d76f718f5_meds.jpg","width":75,"height":75}},"url":"/user/juliwolke/pic/1dzmv/","pic_files":{"640r":{"width":640,"img_url":"http://s0.i1.picplzthumbs.com/upload/img/76/37/ec/7637ecf53c5e75363291bdd981adce9a51173b05_wmeg_00001.jpg","height":427},"100sh":{"width":100,"img_url":"http://s0.i1.picplzthumbs.com/upload/img/76/37/ec/7637ecf53c5e75363291bdd981adce9a51173b05_t200s_00001.jpg","height":100},"320rh":{"width":320,"img_url":"http://s0.i1.picplzthumbs.com/upload/img/76/37/ec/7637ecf53c5e75363291bdd981adce9a51173b05_mmed_00001.jpg","height":213}},"caption":"good night","comment_count":3,"like_count":30,"date":1338068854,"id":11095095},{"view_count":13,"creator":{"username":"foofighters41","display_name":"foofighters42","following_count":512,"follower_count":362,"id":1117352,"icon":{"url":"http://s0.ui1.picplzthumbs.com/usericons/2a/d2/8b/2ad28b85fc954d7802758b5279fc767d47398504_meds.jpg","width":75,"height":75}},"url":"/user/foofighters41/pic/1dw9f/","pic_files":{"640r":{"width":600,"img_url":"http://s0.i1.picplzthumbs.com/upload/img/e7/7d/b0/e77db0bcbfdbba01b25e83aaea67c229c12b5690_wmeg.jpg","height":640},"100sh":{"width":100,"img_url":"http://s0.i1.picplzthumbs.com/upload/img/e7/7d/b0/e77db0bcbfdbba01b25e83aaea67c229c12b5690_t200s.jpg","height":100},"320rh":{"width":300,"img_url":"http://s0.i1.picplzthumbs.com/upload/img/e7/7d/b0/e77db0bcbfdbba01b25e83aaea67c229c12b5690_mmed.jpg","height":320}},"caption":"","comment_count":0,"like_count":19,"date":1338075496,"id":11096406},{"view_count":6,"creator":{"username":"juliwolke","display_name":"Lila","following_count":558,"follower_count":1389,"id":967188,"icon":{"url":"http://s2.ui1.picplzthumbs.com/usericons/03/5a/c4/035ac4ecec13515383c64851105c192d76f718f5_meds.jpg","width":75,"height":75}},"url":"/user/juliwolke/pic/1dmm1/","pic_files":{"640r":{"width":640,"img_url":"http://s1.i1.picplzthumbs.com/upload/img/2d/1c/f7/2d1cf77fdbb66a2abf60baeb18c5d1bd6d5e7d93_wmeg.jpg","height":278},"100sh":{"width":100,"img_url":"http://s1.i1.picplzthumbs.com/upload/img/2d/1c/f7/2d1cf77fdbb66a2abf60baeb18c5d1bd6d5e7d93_t200s.jpg","height":100},"320rh":{"width":320,"img_url":"http://s1.i1.picplzthumbs.com/upload/img/2d/1c/f7/2d1cf77fdbb66a2abf60baeb18c5d1bd6d5e7d93_mmed.jpg","height":139}},"caption":"sunset 26.05.12","comment_count":0,"like_count":39,"date":1338065041,"id":11094193},{"view_count":3,"creator":{"username":"nadeshiko","display_name":"nadeshiko","following_count":500,"follower_count":1356,"id":514200,"icon":{"url":"http://s1.ui1.picplzthumbs.com/usericons/05/fe/6a/05fe6a52117ba0431a547179e8eabb191126fcab_meds.jpg","width":75,"height":75}},"url":"/user/nadeshiko/pic/1dw6c/","pic_files":{"640r":{"width":640,"img_url":"http://s1.i1.picplzthumbs.com/upload/img/3d/e6/11/3de611a634002ef36c765211a05947e13f293116_wmeg_00001.jpg","height":360},"100sh":{"width":100,"img_url":"http://s1.i1.picplzthumbs.com/upload/img/3d/e6/11/3de611a634002ef36c765211a05947e13f293116_t200s_00001.jpg","height":100},"320rh":{"width":320,"img_url":"http://s1.i1.picplzthumbs.com/upload/img/3d/e6/11/3de611a634002ef36c765211a05947e13f293116_mmed_00001.jpg","height":180}},"caption":"\u898b\u3066\u308b... \u3057\u3070\u3089\u304f\u306e\u9593\u3001\u7768\u307f\u5408\u3044\u306f\u7d9a\u304f","comment_count":1,"like_count":18,"date":1338074209,"id":11096176},{"view_count":1,"creator":{"username":"saoritaka","display_name":"\u3055\u304a\u308a\uff08SAORI\uff09","following_count":249,"follower_count":343,"id":1299650,"icon":{"url":"http://s2.ui1.picplzthumbs.com/usericons/61/7f/20/617f20c2e8698d78bed5926cc93a416c65b21079_meds.jpg","width":75,"height":75}},"url":"/user/saoritaka/pic/1xp80/","pic_files":{"640r":{"width":640,"img_url":"http://s0.i1.picplzthumbs.com/upload/img/d2/d5/d6/d2d5d6c28ab1c5c0f4ebadb3979f478cdcd624cc_wmeg_00001.jpg","height":480},"100sh":{"width":100,"img_url":"http://s0.i1.picplzthumbs.com/upload/img/d2/d5/d6/d2d5d6c28ab1c5c0f4ebadb3979f478cdcd624cc_t200s_00001.jpg","height":100},"320rh":{"width":320,"img_url":"http://s0.i1.picplzthumbs.com/upload/img/d2/d5/d6/d2d5d6c28ab1c5c0f4ebadb3979f478cdcd624cc_mmed_00001.jpg","height":240}},"caption":"\u30dd\u30d4\u30fc\u304b\u306a","comment_count":0,"like_count":5,"date":1338081045,"id":11097672},{"city":{"url":"/city/schmalkalden-de/","id":33232,"name":"Schmalkalden, Germany"},"creator":{"username":"larsgebauer","display_name":"Lars Gebauer","following_count":7071,"follower_count":5536,"id":4473,"icon":{"url":"http://s1.ui1.picplzthumbs.com/usericons/17/31/53/173153eb4fb7d9fff573e44fece8a8226a6f3e90_meds.jpg","width":75,"height":75}},"url":"/user/larsgebauer/pic/1dmr5/","pic_files":{"640r":{"width":640,"img_url":"http://s2.i1.picplzthumbs.com/upload/img/19/d8/66/19d866c24796f6e2fec860ba5936bfb98aacfafe_wmeg_00001.jpg","height":640},"100sh":{"width":100,"img_url":"http://s2.i1.picplzthumbs.com/upload/img/19/d8/66/19d866c24796f6e2fec860ba5936bfb98aacfafe_t200s_00001.jpg","height":100},"320rh":{"width":320,"img_url":"http://s2.i1.picplzthumbs.com/upload/img/19/d8/66/19d866c24796f6e2fec860ba5936bfb98aacfafe_mmed_00001.jpg","height":320}},"view_count":31,"caption":"Alte Schlepper und junge Weiber sind die besten Zeitvertreiber.","comment_count":1,"like_count":47,"place":{"url":"/pics/sportplatz-niederschmalkalden-schmalkalden-thuringen/","id":343632,"name":"Sportplatz Niederschmalkalden"},"date":1338061820,"id":11093453},{"view_count":19,"creator":{"username":"gotenba","display_name":"suruga","following_count":2108,"follower_count":6837,"id":232354,"icon":{"url":"http://s1.ui1.picplzthumbs.com/usericons/47/77/4a/47774a177d4ad9a37fd9d292f20df9fbff509b4a_meds.jpg","width":75,"height":75}},"url":"/user/gotenba/pic/1dsw0/","pic_files":{"640r":{"width":426,"img_url":"http://s0.i1.picplzthumbs.com/upload/img/2a/df/29/2adf292a70b3d6a73cd4dadc2e0308b75b28cac8_wmeg.jpg","height":640},"100sh":{"width":100,"img_url":"http://s0.i1.picplzthumbs.com/upload/img/2a/df/29/2adf292a70b3d6a73cd4dadc2e0308b75b28cac8_t200s.jpg","height":100},"320rh":{"width":213,"img_url":"http://s0.i1.picplzthumbs.com/upload/img/2a/df/29/2adf292a70b3d6a73cd4dadc2e0308b75b28cac8_mmed.jpg","height":320}},"caption":"Lucky seven.  Good morning! :D","comment_count":2,"like_count":18,"date":1338073680,"id":11096082},{"view_count":2,"creator":{"username":"soniaccs","display_name":"Sonia S","following_count":318,"follower_count":386,"id":992030,"icon":{"url":"http://s2.ui1.picplzthumbs.com/usericons/9f/35/21/9f3521c8bc603ff9f91f146661e75ae7693926c2_meds.jpg","width":75,"height":75}},"url":"/user/soniaccs/pic/1dwxr/","pic_files":{"640r":{"width":640,"img_url":"http://s1.i1.picplzthumbs.com/upload/img/5c/27/94/5c2794cdfd0fb695688b4276576be7d08da2c4ca_wmeg_00001.jpg","height":480},"100sh":{"width":100,"img_url":"http://s1.i1.picplzthumbs.com/upload/img/5c/27/94/5c2794cdfd0fb695688b4276576be7d08da2c4ca_t200s_00001.jpg","height":100},"320rh":{"width":320,"img_url":"http://s1.i1.picplzthumbs.com/upload/img/5c/27/94/5c2794cdfd0fb695688b4276576be7d08da2c4ca_mmed_00001.jpg","height":240}},"caption":"","comment_count":0,"like_count":11,"date":1338076984,"id":11096731},{"view_count":10,"creator":{"username":"foofighters41","display_name":"foofighters42","following_count":512,"follower_count":362,"id":1117352,"icon":{"url":"http://s0.ui1.picplzthumbs.com/usericons/2a/d2/8b/2ad28b85fc954d7802758b5279fc767d47398504_meds.jpg","width":75,"height":75}},"url":"/user/foofighters41/pic/1dwp9/","pic_files":{"640r":{"width":475,"img_url":"http://s1.i1.picplzthumbs.com/upload/img/fd/c7/f6/fdc7f67e7f1b1c6b6b46719cd740c8ce80b80b0a_wmeg.jpg","height":640},"100sh":{"width":100,"img_url":"http://s1.i1.picplzthumbs.com/upload/img/fd/c7/f6/fdc7f67e7f1b1c6b6b46719cd740c8ce80b80b0a_t200s.jpg","height":100},"320rh":{"width":238,"img_url":"http://s1.i1.picplzthumbs.com/upload/img/fd/c7/f6/fdc7f67e7f1b1c6b6b46719cd740c8ce80b80b0a_mmed.jpg","height":320}},"caption":"","comment_count":0,"like_count":16,"date":1338073858,"id":11096110},{"view_count":2,"creator":{"username":"sekizen1919","display_name":"Sekizen Ichinomiya","following_count":127,"follower_count":221,"id":875581,"icon":{"url":"http://s2.ui1.picplzthumbs.com/usericons/1a/0d/37/1a0d37d6e1e7b041a70bb1053b8e121ef66b2bff_meds.jpg","width":75,"height":75}},"url":"/user/sekizen1919/pic/1dwnr/","pic_files":{"640r":{"width":478,"img_url":"http://s1.i1.picplzthumbs.com/upload/img/97/1c/c6/971cc68c58ab60956fa9176768c005b963b72ad9_wmeg_00001.jpg","height":640},"100sh":{"width":100,"img_url":"http://s1.i1.picplzthumbs.com/upload/img/97/1c/c6/971cc68c58ab60956fa9176768c005b963b72ad9_t200s_00001.jpg","height":100},"320rh":{"width":239,"img_url":"http://s1.i1.picplzthumbs.com/upload/img/97/1c/c6/971cc68c58ab60956fa9176768c005b963b72ad9_mmed_00001.jpg","height":320}},"caption":"\u304a\u306f\u3088\u3046\u30b5\u30f3\u30c7\u30fc\u3001\u4ed5\u4e8b\u3060\u3088\uff5e\u3093","comment_count":3,"like_count":9,"date":1338076576,"id":11096641},{"view_count":8,"creator":{"username":"kinp26","display_name":"tsuyoshi(kin\u306f\u3042\u3060\u540d\u3001\uff5026\u671f\uff09","following_count":237,"follower_count":470,"id":994493,"icon":{"url":"http://s1.ui1.picplzthumbs.com/usericons/98/66/41/986641d713d060b5a748695616b12ad6de26ba7a_meds.jpg","width":75,"height":75}},"url":"/user/kinp26/pic/1dsxj/","pic_files":{"640r":{"width":640,"img_url":"http://s1.i1.picplzthumbs.com/upload/img/4a/12/9b/4a129b051d9303fd06e7a70bce0036a3f8ff3b82_wmeg.jpg","height":480},"100sh":{"width":100,"img_url":"http://s1.i1.picplzthumbs.com/upload/img/4a/12/9b/4a129b051d9303fd06e7a70bce0036a3f8ff3b82_t200s.jpg","height":100},"320rh":{"width":320,"img_url":"http://s1.i1.picplzthumbs.com/upload/img/4a/12/9b/4a129b051d9303fd06e7a70bce0036a3f8ff3b82_mmed.jpg","height":240}},"caption":"0527  \u5fd7\u6469 Morning sun","comment_count":1,"like_count":16,"date":1338072430,"id":11095849},{"view_count":6,"creator":{"username":"engelsvater","display_name":"Oki Wan","following_count":548,"follower_count":674,"id":967425,"icon":{"url":"http://s1.ui1.picplzthumbs.com/usericons/91/dc/58/91dc586e923925fc2e63b4429eee5ad52a0e694e_meds.jpg","width":75,"height":75}},"url":"/user/engelsvater/pic/1dzt0/","pic_files":{"640r":{"width":427,"img_url":"http://s0.i1.picplzthumbs.com/upload/img/3e/2d/f6/3e2df674bf873cf0641e6bee1dcf3cc70dcb04eb_wmeg_00001.jpg","height":640},"100sh":{"width":100,"img_url":"http://s0.i1.picplzthumbs.com/upload/img/3e/2d/f6/3e2df674bf873cf0641e6bee1dcf3cc70dcb04eb_t200s_00001.jpg","height":100},"320rh":{"width":213,"img_url":"http://s0.i1.picplzthumbs.com/upload/img/3e/2d/f6/3e2df674bf873cf0641e6bee1dcf3cc70dcb04eb_mmed_00001.jpg","height":320}},"caption":"Green Strawberrys","comment_count":2,"like_count":29,"date":1338066166,"id":11094462},{"view_count":1,"creator":{"username":"saoritaka","display_name":"\u3055\u304a\u308a\uff08SAORI\uff09","following_count":249,"follower_count":343,"id":1299650,"icon":{"url":"http://s2.ui1.picplzthumbs.com/usericons/61/7f/20/617f20c2e8698d78bed5926cc93a416c65b21079_meds.jpg","width":75,"height":75}},"url":"/user/saoritaka/pic/1xpjq/","pic_files":{"640r":{"width":478,"img_url":"http://s2.i1.picplzthumbs.com/upload/img/a6/55/d3/a655d3904d676c8891aaf17e9b0b758b5e11d5ea_wmeg_00001.jpg","height":640},"100sh":{"width":100,"img_url":"http://s2.i1.picplzthumbs.com/upload/img/a6/55/d3/a655d3904d676c8891aaf17e9b0b758b5e11d5ea_t200s_00001.jpg","height":100},"320rh":{"width":239,"img_url":"http://s2.i1.picplzthumbs.com/upload/img/a6/55/d3/a655d3904d676c8891aaf17e9b0b758b5e11d5ea_mmed_00001.jpg","height":320}},"caption":"\u540d\u524d\u3092\u5fd8\u308c\u3066\u3057\u3082\u3046\u305f\u3002\u82b1\u306e\u8272\u304c\u5909\u5316\u3057\u3066\u3044\u304d\u307e\u3059\u3002\u3059\u3054\u304f\u826f\u3044\u9999\u308a\u82b1\u3002","comment_count":0,"like_count":4,"date":1338080627,"id":11097581},{"city":{"url":"/city/shinshiro-city-jp/","id":19116,"name":"Shinshiro City, Japan"},"creator":{"username":"akkosan","display_name":"\u5bff\u660c\u660e\u5b50","following_count":35,"follower_count":30,"id":1497244,"icon":{"url":"http://s1.ui1.picplzthumbs.com/usericons/4b/15/9b/4b159bf0f9def3f26cc41fa1c1c26fc198ce06c6_meds.jpg","width":75,"height":75}},"url":"/user/akkosan/pic/1dw2w/","pic_files":{"640r":{"width":480,"img_url":"http://s2.i1.picplzthumbs.com/upload/img/39/96/cf/3996cfd49eff1e1c9c587e3b5a1051c4f3bb7821_wmeg_00001.jpg","height":640},"100sh":{"width":100,"img_url":"http://s2.i1.picplzthumbs.com/upload/img/39/96/cf/3996cfd49eff1e1c9c587e3b5a1051c4f3bb7821_t200s_00001.jpg","height":100},"320rh":{"width":240,"img_url":"http://s2.i1.picplzthumbs.com/upload/img/39/96/cf/3996cfd49eff1e1c9c587e3b5a1051c4f3bb7821_mmed_00001.jpg","height":320}},"view_count":3,"caption":"\u7236\u30cf\u30f3\u30c9\u30e1\u30a4\u30c9\u5c4b\u4e45\u6749\u306e\u62db\u304d\u732b","comment_count":11,"like_count":8,"date":1338076164,"id":11096549},{"view_count":0,"creator":{"username":"soniaccs","display_name":"Sonia S","following_count":318,"follower_count":386,"id":992030,"icon":{"url":"http://s2.ui1.picplzthumbs.com/usericons/9f/35/21/9f3521c8bc603ff9f91f146661e75ae7693926c2_meds.jpg","width":75,"height":75}},"url":"/user/soniaccs/pic/1dw5q/","pic_files":{"640r":{"width":640,"img_url":"http://s2.i1.picplzthumbs.com/upload/img/71/ad/f7/71adf79e02ee79c92ebc78f3e65208607920134c_wmeg_00001.jpg","height":384},"100sh":{"width":100,"img_url":"http://s2.i1.picplzthumbs.com/upload/img/71/ad/f7/71adf79e02ee79c92ebc78f3e65208607920134c_t200s_00001.jpg","height":100},"320rh":{"width":320,"img_url":"http://s2.i1.picplzthumbs.com/upload/img/71/ad/f7/71adf79e02ee79c92ebc78f3e65208607920134c_mmed_00001.jpg","height":192}},"caption":"","comment_count":0,"like_count":8,"date":1338077298,"id":11096801},{"view_count":19,"creator":{"username":"canowine","display_name":"John Rinker","following_count":332,"follower_count":355,"id":279341,"icon":{"url":"http://s0.ui1.picplzthumbs.com/usericons/d6/6f/96/d66f96e86ec6f2e67d707067ba0921a8d2a1c0f8_meds.jpg","width":75,"height":75}},"url":"/user/canowine/pic/1ds8v/","pic_files":{"640r":{"width":640,"img_url":"http://s0.i1.picplzthumbs.com/upload/img/1f/62/27/1f6227420a053226c61ad6854a76830c4bdd490f_wmeg.jpg","height":458},"100sh":{"width":100,"img_url":"http://s0.i1.picplzthumbs.com/upload/img/1f/62/27/1f6227420a053226c61ad6854a76830c4bdd490f_t200s.jpg","height":100},"320rh":{"width":320,"img_url":"http://s0.i1.picplzthumbs.com/upload/img/1f/62/27/1f6227420a053226c61ad6854a76830c4bdd490f_mmed.jpg","height":229}},"caption":"Reaching for the sky at Huffman Prairie Flying Field.","comment_count":0,"like_count":13,"date":1338072535,"id":11095875},{"view_count":20,"creator":{"username":"foofighters41","display_name":"foofighters42","following_count":512,"follower_count":362,"id":1117352,"icon":{"url":"http://s0.ui1.picplzthumbs.com/usericons/2a/d2/8b/2ad28b85fc954d7802758b5279fc767d47398504_meds.jpg","width":75,"height":75}},"url":"/user/foofighters41/pic/1ds5s/","pic_files":{"640r":{"width":640,"img_url":"http://s1.i1.picplzthumbs.com/upload/img/32/fb/82/32fb8245c6b7ca0a7bd8ff69240456c6a84bec3a_wmeg.jpg","height":474},"100sh":{"width":100,"img_url":"http://s1.i1.picplzthumbs.com/upload/img/32/fb/82/32fb8245c6b7ca0a7bd8ff69240456c6a84bec3a_t200s.jpg","height":100},"320rh":{"width":320,"img_url":"http://s1.i1.picplzthumbs.com/upload/img/32/fb/82/32fb8245c6b7ca0a7bd8ff69240456c6a84bec3a_mmed.jpg","height":237}},"caption":"Sunday morning!! :-)","comment_count":0,"like_count":13,"date":1338072761,"id":11095918},{"view_count":11,"creator":{"username":"foofighters41","display_name":"foofighters42","following_count":512,"follower_count":362,"id":1117352,"icon":{"url":"http://s0.ui1.picplzthumbs.com/usericons/2a/d2/8b/2ad28b85fc954d7802758b5279fc767d47398504_meds.jpg","width":75,"height":75}},"url":"/user/foofighters41/pic/1dwf2/","pic_files":{"640r":{"width":483,"img_url":"http://s2.i1.picplzthumbs.com/upload/img/1e/8e/fb/1e8efbef036946ca04910deb34092262df3862c5_wmeg.jpg","height":640},"100sh":{"width":100,"img_url":"http://s2.i1.picplzthumbs.com/upload/img/1e/8e/fb/1e8efbef036946ca04910deb34092262df3862c5_t200s.jpg","height":100},"320rh":{"width":242,"img_url":"http://s2.i1.picplzthumbs.com/upload/img/1e/8e/fb/1e8efbef036946ca04910deb34092262df3862c5_mmed.jpg","height":320}},"caption":"","comment_count":0,"like_count":13,"date":1338074858,"id":11096294},{"view_count":19,"creator":{"username":"foofighters41","display_name":"foofighters42","following_count":512,"follower_count":362,"id":1117352,"icon":{"url":"http://s0.ui1.picplzthumbs.com/usericons/2a/d2/8b/2ad28b85fc954d7802758b5279fc767d47398504_meds.jpg","width":75,"height":75}},"url":"/user/foofighters41/pic/1dwhw/","pic_files":{"640r":{"width":640,"img_url":"http://s2.i1.picplzthumbs.com/upload/img/12/be/1b/12be1b3350f4000b5caa0c39a84b0ef282215139_wmeg_00001.jpg","height":474},"100sh":{"width":100,"img_url":"http://s2.i1.picplzthumbs.com/upload/img/12/be/1b/12be1b3350f4000b5caa0c39a84b0ef282215139_t200s_00001.jpg","height":100},"320rh":{"width":320,"img_url":"http://s2.i1.picplzthumbs.com/upload/img/12/be/1b/12be1b3350f4000b5caa0c39a84b0ef282215139_mmed_00001.jpg","height":237}},"caption":"","comment_count":0,"like_count":13,"date":1338074090,"id":11096249},{"view_count":19,"creator":{"username":"foofighters41","display_name":"foofighters42","following_count":512,"follower_count":362,"id":1117352,"icon":{"url":"http://s0.ui1.picplzthumbs.com/usericons/2a/d2/8b/2ad28b85fc954d7802758b5279fc767d47398504_meds.jpg","width":75,"height":75}},"url":"/user/foofighters41/pic/1dwbs/","pic_files":{"640r":{"width":640,"img_url":"http://s1.i1.picplzthumbs.com/upload/img/39/f8/7f/39f87f7d5fbbcddd03fedec0ac12bad488dab1af_wmeg.jpg","height":480},"100sh":{"width":100,"img_url":"http://s1.i1.picplzthumbs.com/upload/img/39/f8/7f/39f87f7d5fbbcddd03fedec0ac12bad488dab1af_t200s.jpg","height":100},"320rh":{"width":320,"img_url":"http://s1.i1.picplzthumbs.com/upload/img/39/f8/7f/39f87f7d5fbbcddd03fedec0ac12bad488dab1af_mmed.jpg","height":240}},"caption":"","comment_count":0,"like_count":13,"date":1338075131,"id":11096338},{"view_count":26,"creator":{"username":"juliwolke","display_name":"Lila","following_count":558,"follower_count":1389,"id":967188,"icon":{"url":"http://s2.ui1.picplzthumbs.com/usericons/03/5a/c4/035ac4ecec13515383c64851105c192d76f718f5_meds.jpg","width":75,"height":75}},"url":"/user/juliwolke/pic/1dm5r/","pic_files":{"640r":{"width":640,"img_url":"http://s1.i1.picplzthumbs.com/upload/img/94/d1/fe/94d1fe28e0626d2882024045d8b61233c77d8407_wmeg.jpg","height":324},"100sh":{"width":100,"img_url":"http://s1.i1.picplzthumbs.com/upload/img/94/d1/fe/94d1fe28e0626d2882024045d8b61233c77d8407_t200s.jpg","height":100},"320rh":{"width":320,"img_url":"http://s1.i1.picplzthumbs.com/upload/img/94/d1/fe/94d1fe28e0626d2882024045d8b61233c77d8407_mmed.jpg","height":162}},"caption":"today ;) good evening everyone \u2665","comment_count":0,"like_count":31,"date":1338064648,"id":11094091},{"view_count":19,"creator":{"username":"kinp26","display_name":"tsuyoshi(kin\u306f\u3042\u3060\u540d\u3001\uff5026\u671f\uff09","following_count":237,"follower_count":470,"id":994493,"icon":{"url":"http://s1.ui1.picplzthumbs.com/usericons/98/66/41/986641d713d060b5a748695616b12ad6de26ba7a_meds.jpg","width":75,"height":75}},"url":"/user/kinp26/pic/1ds5b/","pic_files":{"640r":{"width":640,"img_url":"http://s1.i1.picplzthumbs.com/upload/img/1a/5e/32/1a5e3215b69f0a60d729d76414a3b163dcba51e5_wmeg.jpg","height":480},"100sh":{"width":100,"img_url":"http://s1.i1.picplzthumbs.com/upload/img/1a/5e/32/1a5e3215b69f0a60d729d76414a3b163dcba51e5_t200s.jpg","height":100},"320rh":{"width":320,"img_url":"http://s1.i1.picplzthumbs.com/upload/img/1a/5e/32/1a5e3215b69f0a60d729d76414a3b163dcba51e5_mmed.jpg","height":240}},"caption":"0527 \u5fd7\u6469  Breakwater","comment_count":0,"like_count":12,"date":1338072630,"id":11095897},{"view_count":0,"creator":{"username":"skybluesky","display_name":"sorato:","following_count":18,"follower_count":128,"id":1477975,"icon":{"url":"http://s0.ui1.picplzthumbs.com/usericons/7f/e6/9c/7fe69cca54076ff6a298e42be8608d486cc79baa_meds.jpg","width":75,"height":75}},"url":"/user/skybluesky/pic/1dszw/","pic_files":{"640r":{"width":442,"img_url":"http://s2.i1.picplzthumbs.com/upload/img/b9/1c/80/b91c80daefe52d3f072c285c332861390a4d8b0c_wmeg.jpg","height":640},"100sh":{"width":100,"img_url":"http://s2.i1.picplzthumbs.com/upload/img/b9/1c/80/b91c80daefe52d3f072c285c332861390a4d8b0c_t200s.jpg","height":100},"320rh":{"width":221,"img_url":"http://s2.i1.picplzthumbs.com/upload/img/b9/1c/80/b91c80daefe52d3f072c285c332861390a4d8b0c_mmed.jpg","height":320}},"caption":"\u300c\u7a7a\u306e\u5b50\u305f\u3061\u300d\u306e\u82b1 \u2162","comment_count":0,"like_count":11,"date":1338073400,"id":11096039},{"view_count":4,"creator":{"username":"gmarti","display_name":"Gabriel","following_count":268,"follower_count":1128,"id":823791,"icon":{"url":"http://s0.ui1.picplzthumbs.com/usericons/5e/e3/2a/5ee32aaf4aa5f2ba85c268e48e431cfd95bbd911_meds.jpg","width":75,"height":75}},"url":"/user/gmarti/pic/1dwpk/","pic_files":{"640r":{"width":640,"img_url":"http://s0.i1.picplzthumbs.com/upload/img/4b/5e/72/4b5e7275d9738141566d59a1e5799d90bb6cef3c_wmeg.jpg","height":640},"100sh":{"width":100,"img_url":"http://s0.i1.picplzthumbs.com/upload/img/4b/5e/72/4b5e7275d9738141566d59a1e5799d90bb6cef3c_t200s.jpg","height":100},"320rh":{"width":320,"img_url":"http://s0.i1.picplzthumbs.com/upload/img/4b/5e/72/4b5e7275d9738141566d59a1e5799d90bb6cef3c_mmed.jpg","height":320}},"caption":"Water is life","comment_count":0,"like_count":11,"date":1338073932,"id":11096109},{"view_count":12,"creator":{"username":"foofighters41","display_name":"foofighters42","following_count":512,"follower_count":362,"id":1117352,"icon":{"url":"http://s0.ui1.picplzthumbs.com/usericons/2a/d2/8b/2ad28b85fc954d7802758b5279fc767d47398504_meds.jpg","width":75,"height":75}},"url":"/user/foofighters41/pic/1dwtp/","pic_files":{"640r":{"width":640,"img_url":"http://s0.i1.picplzthumbs.com/upload/img/c3/f8/71/c3f8712443579f15e8adc825d58f76d5dc3898d9_wmeg.jpg","height":474},"100sh":{"width":100,"img_url":"http://s0.i1.picplzthumbs.com/upload/img/c3/f8/71/c3f8712443579f15e8adc825d58f76d5dc3898d9_t200s.jpg","height":100},"320rh":{"width":320,"img_url":"http://s0.i1.picplzthumbs.com/upload/img/c3/f8/71/c3f8712443579f15e8adc825d58f76d5dc3898d9_mmed.jpg","height":237}},"caption":"","comment_count":0,"like_count":11,"date":1338074614,"id":11096250},{"view_count":4,"creator":{"username":"vromobethi","display_name":"CD","following_count":176,"follower_count":354,"id":1270326,"icon":{"url":"http://a2.picplzthumbs.com/i/FwCNRNyPZJGlqJMyQXwM2wgQ_k4.png","width":100,"height":100}},"url":"/user/vromobethi/pic/1d5jb/","pic_files":{"640r":{"width":427,"img_url":"http://s1.i1.picplzthumbs.com/upload/img/14/cc/ac/14ccac7927d75d1afbc21b3ea5b49e4ae0f8d113_wmeg.jpg","height":640},"100sh":{"width":100,"img_url":"http://s1.i1.picplzthumbs.com/upload/img/14/cc/ac/14ccac7927d75d1afbc21b3ea5b49e4ae0f8d113_t200s.jpg","height":100},"320rh":{"width":213,"img_url":"http://s1.i1.picplzthumbs.com/upload/img/14/cc/ac/14ccac7927d75d1afbc21b3ea5b49e4ae0f8d113_mmed.jpg","height":320}},"caption":"","comment_count":0,"like_count":16,"date":1338050595,"id":11091277},{"view_count":9,"creator":{"username":"pylvaelaeinen","display_name":"Markus Pentti Pylvaelaeinen","following_count":440,"follower_count":807,"id":776067,"icon":{"url":"http://s2.ui1.picplzthumbs.com/usericons/64/91/f7/6491f7ab05f2edb5fa7254e2f8a2a18649323e8b_meds.jpg","width":75,"height":75}},"url":"/user/pylvaelaeinen/pic/1dmzx/","pic_files":{"640r":{"width":476,"img_url":"http://s0.i1.picplzthumbs.com/upload/img/a5/08/b3/a508b3cbf28e665b7c66a31f1a10795009395b75_wmeg.jpg","height":640},"100sh":{"width":100,"img_url":"http://s0.i1.picplzthumbs.com/upload/img/a5/08/b3/a508b3cbf28e665b7c66a31f1a10795009395b75_t200s.jpg","height":100},"320rh":{"width":238,"img_url":"http://s0.i1.picplzthumbs.com/upload/img/a5/08/b3/a508b3cbf28e665b7c66a31f1a10795009395b75_mmed.jpg","height":320}},"caption":"lantern at castle schwerin","comment_count":1,"like_count":21,"date":1338065204,"id":11094231},{"view_count":0,"creator":{"username":"redplay","display_name":"redWORLD","following_count":53,"follower_count":68,"id":1343485,"icon":{"url":"http://a2.picplzthumbs.com/i/FwCNRNyPZJGlqJMyQXwM2wgQ_k4.png","width":100,"height":100}},"url":"/user/redplay/pic/1xp05/","pic_files":{"640r":{"width":640,"img_url":"http://s2.i1.picplzthumbs.com/upload/img/a1/bf/41/a1bf41fe17af6f92fdcc9f34f7498b2dc2eb88b6_wmeg_00001.jpg","height":480},"100sh":{"width":100,"img_url":"http://s2.i1.picplzthumbs.com/upload/img/a1/bf/41/a1bf41fe17af6f92fdcc9f34f7498b2dc2eb88b6_t200s_00001.jpg","height":100},"320rh":{"width":320,"img_url":"http://s2.i1.picplzthumbs.com/upload/img/a1/bf/41/a1bf41fe17af6f92fdcc9f34f7498b2dc2eb88b6_mmed_00001.jpg","height":240}},"caption":"\u304a\u3084\u3064\u306e\u6642\u9593","comment_count":0,"like_count":3,"date":1337439489,"id":11097383},{"view_count":14,"creator":{"username":"uchippo","display_name":"uchippo","following_count":206,"follower_count":357,"id":601279,"icon":{"url":"http://s0.ui1.picplzthumbs.com/usericons/32/54/37/32543719f874f6c2652af1dbf9751c461639d132_meds.jpg","width":75,"height":75}},"url":"/user/uchippo/pic/1xplz/","pic_files":{"640r":{"width":640,"img_url":"http://s0.i1.picplzthumbs.com/upload/img/f9/b3/1a/f9b31a86e3704580b20a108cb6d4b27276d2a75d_wmeg_00001.jpg","height":480},"100sh":{"width":100,"img_url":"http://s0.i1.picplzthumbs.com/upload/img/f9/b3/1a/f9b31a86e3704580b20a108cb6d4b27276d2a75d_t200s_00001.jpg","height":100},"320rh":{"width":320,"img_url":"http://s0.i1.picplzthumbs.com/upload/img/f9/b3/1a/f9b31a86e3704580b20a108cb6d4b27276d2a75d_mmed_00001.jpg","height":240}},"caption":"\u4eca\u65e5\u306f\u78ef\u3067\u4e57\u308a\u307e\u3059\u3002","comment_count":2,"like_count":3,"date":1338080463,"id":11097537},{"view_count":16,"creator":{"username":"nekoashinatsu","display_name":"natsu","following_count":70,"follower_count":309,"id":999637,"icon":{"url":"http://s0.ui1.picplzthumbs.com/usericons/4c/04/7f/4c047faf8f2ea7f12c48f979ddb70f33cdb0b278_meds.jpg","width":75,"height":75}},"url":"/user/nekoashinatsu/pic/1xpbm/","pic_files":{"640r":{"width":640,"img_url":"http://s2.i1.picplzthumbs.com/upload/img/d8/43/ae/d843aee87f544f82eae6df6598f7abaa39748c86_wmeg.jpg","height":480},"100sh":{"width":100,"img_url":"http://s2.i1.picplzthumbs.com/upload/img/d8/43/ae/d843aee87f544f82eae6df6598f7abaa39748c86_t200s.jpg","height":100},"320rh":{"width":320,"img_url":"http://s2.i1.picplzthumbs.com/upload/img/d8/43/ae/d843aee87f544f82eae6df6598f7abaa39748c86_mmed.jpg","height":240}},"caption":"","comment_count":0,"like_count":6,"date":1338078693,"id":11097236},{"view_count":16,"creator":{"username":"engelsvater","display_name":"Oki Wan","following_count":548,"follower_count":674,"id":967425,"icon":{"url":"http://s1.ui1.picplzthumbs.com/usericons/91/dc/58/91dc586e923925fc2e63b4429eee5ad52a0e694e_meds.jpg","width":75,"height":75}},"url":"/user/engelsvater/pic/1dsbs/","pic_files":{"640r":{"width":640,"img_url":"http://s1.i1.picplzthumbs.com/upload/img/ea/f4/13/eaf41360754bbfb70fa92f9de56e39668877ce3f_wmeg_00001.jpg","height":427},"100sh":{"width":100,"img_url":"http://s1.i1.picplzthumbs.com/upload/img/ea/f4/13/eaf41360754bbfb70fa92f9de56e39668877ce3f_t200s_00001.jpg","height":100},"320rh":{"width":320,"img_url":"http://s1.i1.picplzthumbs.com/upload/img/ea/f4/13/eaf41360754bbfb70fa92f9de56e39668877ce3f_mmed_00001.jpg","height":213}},"caption":"Koi-Fish","comment_count":0,"like_count":15,"date":1338070454,"id":11095438},{"view_count":30,"creator":{"username":"cookieraider","display_name":"Maria","following_count":1805,"follower_count":749,"id":1488282,"icon":{"url":"http://s2.ui1.picplzthumbs.com/usericons/b6/bf/7a/b6bf7a91bb10aae6b70cea7472caa9f698328e79_meds.jpg","width":75,"height":75}},"url":"/user/cookieraider/pic/1d5bs/","pic_files":{"640r":{"width":400,"img_url":"http://s1.i1.picplzthumbs.com/upload/img/a8/69/3a/a8693a1171e6b9bcd02216da874c3b01752cb6d3_400r.jpg","height":400},"100sh":{"width":100,"img_url":"http://s1.i1.picplzthumbs.com/upload/img/a8/69/3a/a8693a1171e6b9bcd02216da874c3b01752cb6d3_t200s.jpg","height":100},"320rh":{"width":320,"img_url":"http://s1.i1.picplzthumbs.com/upload/img/a8/69/3a/a8693a1171e6b9bcd02216da874c3b01752cb6d3_mmed.jpg","height":320}},"caption":"Simple black heels :)","comment_count":1,"like_count":62,"date":1338048716,"id":11090938},{"view_count":8,"creator":{"username":"winterqueen","display_name":"Saundra","following_count":652,"follower_count":587,"id":343365,"icon":{"url":"http://s1.ui1.picplzthumbs.com/usericons/21/a4/61/21a461c17502286304ae10748a35f3dcb8d37334_meds.jpg","width":75,"height":75}},"url":"/user/winterqueen/pic/1dsxk/","pic_files":{"640r":{"width":361,"img_url":"http://s0.i1.picplzthumbs.com/upload/img/a1/74/f8/a174f8012766962a81eb17afce728fd21ef5a10d_wmeg.jpg","height":640},"100sh":{"width":100,"img_url":"http://s0.i1.picplzthumbs.com/upload/img/a1/74/f8/a174f8012766962a81eb17afce728fd21ef5a10d_t200s.jpg","height":100},"320rh":{"width":180,"img_url":"http://s0.i1.picplzthumbs.com/upload/img/a1/74/f8/a174f8012766962a81eb17afce728fd21ef5a10d_mmed.jpg","height":320}},"caption":"","comment_count":0,"like_count":9,"date":1338072407,"id":11095839},{"view_count":2,"creator":{"username":"gmarti","display_name":"Gabriel","following_count":268,"follower_count":1128,"id":823791,"icon":{"url":"http://s0.ui1.picplzthumbs.com/usericons/5e/e3/2a/5ee32aaf4aa5f2ba85c268e48e431cfd95bbd911_meds.jpg","width":75,"height":75}},"url":"/user/gmarti/pic/1dwpf/","pic_files":{"640r":{"width":640,"img_url":"http://s0.i1.picplzthumbs.com/upload/img/f6/1a/bd/f61abdf522f56390870ee690aa49d2ecb55a4c10_wmeg.jpg","height":640},"100sh":{"width":100,"img_url":"http://s0.i1.picplzthumbs.com/upload/img/f6/1a/bd/f61abdf522f56390870ee690aa49d2ecb55a4c10_t200s.jpg","height":100},"320rh":{"width":320,"img_url":"http://s0.i1.picplzthumbs.com/upload/img/f6/1a/bd/f61abdf522f56390870ee690aa49d2ecb55a4c10_mmed.jpg","height":320}},"caption":"Waiting","comment_count":0,"like_count":9,"date":1338073906,"id":11096106},{"view_count":31,"creator":{"username":"eddie1856","display_name":"Eddie jacob","following_count":7014,"follower_count":8798,"id":304123,"icon":{"url":"http://s0.ui1.picplzthumbs.com/usericons/59/aa/5a/59aa5a54ce7a570ae86730b5e0a85c3fcd831518_meds.jpg","width":75,"height":75}},"url":"/user/eddie1856/pic/1dd03/","pic_files":{"640r":{"width":640,"img_url":"http://s2.i1.picplzthumbs.com/upload/img/77/09/34/7709344aca81fe899cc3587786679e7960005800_wmeg_00001.jpg","height":421},"100sh":{"width":100,"img_url":"http://s2.i1.picplzthumbs.com/upload/img/77/09/34/7709344aca81fe899cc3587786679e7960005800_t200s_00001.jpg","height":100},"320rh":{"width":320,"img_url":"http://s2.i1.picplzthumbs.com/upload/img/77/09/34/7709344aca81fe899cc3587786679e7960005800_mmed_00001.jpg","height":210}},"caption":"","comment_count":7,"like_count":106,"date":1338032374,"id":11088368},{"view_count":5,"creator":{"username":"pylvaelaeinen","display_name":"Markus Pentti Pylvaelaeinen","following_count":440,"follower_count":807,"id":776067,"icon":{"url":"http://s2.ui1.picplzthumbs.com/usericons/64/91/f7/6491f7ab05f2edb5fa7254e2f8a2a18649323e8b_meds.jpg","width":75,"height":75}},"url":"/user/pylvaelaeinen/pic/1dmzg/","pic_files":{"640r":{"width":480,"img_url":"http://s0.i1.picplzthumbs.com/upload/img/53/b6/49/53b64944e92a00dfafdab3ac6827cc65f1bd7390_wmeg.jpg","height":640},"100sh":{"width":100,"img_url":"http://s0.i1.picplzthumbs.com/upload/img/53/b6/49/53b64944e92a00dfafdab3ac6827cc65f1bd7390_t200s.jpg","height":100},"320rh":{"width":240,"img_url":"http://s0.i1.picplzthumbs.com/upload/img/53/b6/49/53b64944e92a00dfafdab3ac6827cc65f1bd7390_mmed.jpg","height":320}},"caption":"equestrian monument 2 at castle schwerin","comment_count":0,"like_count":17,"date":1338065140,"id":11094213},{"view_count":11,"creator":{"username":"esat","display_name":"Esat","following_count":186,"follower_count":221,"id":1260376,"icon":{"url":"http://s1.ui1.picplzthumbs.com/usericons/ca/1c/d7/ca1cd7adaa37ff68a2cee28c33ddd9871fa8f0f7_meds.jpg","width":75,"height":75}},"url":"/user/esat/pic/1dmkn/","pic_files":{"640r":{"width":480,"img_url":"http://s0.i1.picplzthumbs.com/upload/img/11/ce/4e/11ce4e6ed8e71c7bf3a57d67072f786d8066e75c_wmeg.jpg","height":640},"100sh":{"width":100,"img_url":"http://s0.i1.picplzthumbs.com/upload/img/11/ce/4e/11ce4e6ed8e71c7bf3a57d67072f786d8066e75c_t200s.jpg","height":100},"320rh":{"width":240,"img_url":"http://s0.i1.picplzthumbs.com/upload/img/11/ce/4e/11ce4e6ed8e71c7bf3a57d67072f786d8066e75c_mmed.jpg","height":320}},"caption":"","comment_count":0,"like_count":22,"date":1338062971,"id":11093688},{"view_count":2,"creator":{"username":"gmarti","display_name":"Gabriel","following_count":268,"follower_count":1128,"id":823791,"icon":{"url":"http://s0.ui1.picplzthumbs.com/usericons/5e/e3/2a/5ee32aaf4aa5f2ba85c268e48e431cfd95bbd911_meds.jpg","width":75,"height":75}},"url":"/user/gmarti/pic/1dszl/","pic_files":{"640r":{"width":480,"img_url":"http://s2.i1.picplzthumbs.com/upload/img/ad/33/39/ad33396e64f906547b08eed3b86e00d916c7cad2_wmeg.jpg","height":640},"100sh":{"width":100,"img_url":"http://s2.i1.picplzthumbs.com/upload/img/ad/33/39/ad33396e64f906547b08eed3b86e00d916c7cad2_t200s.jpg","height":100},"320rh":{"width":240,"img_url":"http://s2.i1.picplzthumbs.com/upload/img/ad/33/39/ad33396e64f906547b08eed3b86e00d916c7cad2_mmed.jpg","height":320}},"caption":"For ever","comment_count":0,"like_count":8,"date":1338073437,"id":11096027},{"view_count":10,"creator":{"username":"uyoent","display_name":"UYOENT","following_count":2437,"follower_count":3340,"id":145765,"icon":{"url":"http://s0.ui1.picplzthumbs.com/usericons/92/9f/f2/929ff2399311f16b3f7e6eab8e42f72eafdaef3f_meds.jpg","width":75,"height":75}},"url":"/user/uyoent/pic/1d59l/","pic_files":{"640r":{"width":640,"img_url":"http://s2.i1.picplzthumbs.com/upload/img/5d/c5/51/5dc5519814d05b0875d4e8cfca61bc833fae1bac_wmeg_00001.jpg","height":478},"100sh":{"width":100,"img_url":"http://s2.i1.picplzthumbs.com/upload/img/5d/c5/51/5dc5519814d05b0875d4e8cfca61bc833fae1bac_t200s_00001.jpg","height":100},"320rh":{"width":320,"img_url":"http://s2.i1.picplzthumbs.com/upload/img/5d/c5/51/5dc5519814d05b0875d4e8cfca61bc833fae1bac_mmed_00001.jpg","height":239}},"caption":"In my place","comment_count":3,"like_count":50,"date":1338048980,"id":11091017},{"view_count":3,"creator":{"username":"gmarti","display_name":"Gabriel","following_count":268,"follower_count":1128,"id":823791,"icon":{"url":"http://s0.ui1.picplzthumbs.com/usericons/5e/e3/2a/5ee32aaf4aa5f2ba85c268e48e431cfd95bbd911_meds.jpg","width":75,"height":75}},"url":"/user/gmarti/pic/1dmf1/","pic_files":{"640r":{"width":640,"img_url":"http://s1.i1.picplzthumbs.com/upload/img/50/40/a4/5040a41c0884b857619318b1189717916dd539cd_wmeg_00001.jpg","height":480},"100sh":{"width":100,"img_url":"http://s1.i1.picplzthumbs.com/upload/img/50/40/a4/5040a41c0884b857619318b1189717916dd539cd_t200s_00001.jpg","height":100},"320rh":{"width":320,"img_url":"http://s1.i1.picplzthumbs.com/upload/img/50/40/a4/5040a41c0884b857619318b1189717916dd539cd_mmed_00001.jpg","height":240}},"caption":"","comment_count":0,"like_count":21,"date":1338062581,"id":11093593},{"view_count":3,"creator":{"username":"pylvaelaeinen","display_name":"Markus Pentti Pylvaelaeinen","following_count":440,"follower_count":807,"id":776067,"icon":{"url":"http://s2.ui1.picplzthumbs.com/usericons/64/91/f7/6491f7ab05f2edb5fa7254e2f8a2a18649323e8b_meds.jpg","width":75,"height":75}},"url":"/user/pylvaelaeinen/pic/1dmml/","pic_files":{"640r":{"width":480,"img_url":"http://s2.i1.picplzthumbs.com/upload/img/4b/ec/44/4bec44b16ffaff55304cf339489729a45a126583_wmeg.jpg","height":640},"100sh":{"width":100,"img_url":"http://s2.i1.picplzthumbs.com/upload/img/4b/ec/44/4bec44b16ffaff55304cf339489729a45a126583_t200s.jpg","height":100},"320rh":{"width":240,"img_url":"http://s2.i1.picplzthumbs.com/upload/img/4b/ec/44/4bec44b16ffaff55304cf339489729a45a126583_mmed.jpg","height":320}},"caption":"equestrian monument at castle schwerin","comment_count":0,"like_count":15,"date":1338065056,"id":11094197},{"city":{"url":"/city/berlin-de/","id":551,"name":"Berlin, Germany"},"creator":{"username":"abbyasian","display_name":"abby_asian","following_count":412,"follower_count":274,"id":1439353,"icon":{"url":"http://s2.ui1.picplzthumbs.com/usericons/5b/dc/c7/5bdcc7eb85785f12c12cf636460dda49fd2d3c34_meds.jpg","width":75,"height":75}},"url":"/user/abbyasian/pic/1dzj7/","pic_files":{"640r":{"width":478,"img_url":"http://s0.i1.picplzthumbs.com/upload/img/75/bf/3c/75bf3caba578f0985b0176f9bfa439551cc0bf07_wmeg_00001.jpg","height":640},"100sh":{"width":100,"img_url":"http://s0.i1.picplzthumbs.com/upload/img/75/bf/3c/75bf3caba578f0985b0176f9bfa439551cc0bf07_t200s_00001.jpg","height":100},"320rh":{"width":239,"img_url":"http://s0.i1.picplzthumbs.com/upload/img/75/bf/3c/75bf3caba578f0985b0176f9bfa439551cc0bf07_mmed_00001.jpg","height":320}},"view_count":10,"caption":"","comment_count":0,"like_count":15,"date":1338057071,"id":11094894},{"view_count":17,"creator":{"username":"dikov66","display_name":"Yonko Yliev","following_count":1119,"follower_count":2550,"id":251776,"icon":{"url":"http://s2.ui1.picplzthumbs.com/usericons/f4/81/a0/f481a0bec5d326f20d37a14251daadc61b5f6919_meds.jpg","width":75,"height":75}},"url":"/user/dikov66/pic/1d405/","pic_files":{"640r":{"width":267,"img_url":"http://s2.i1.picplzthumbs.com/upload/img/f2/33/69/f23369cbb88b1215c5640ba780ff7d61c757f1d6_400r.jpg","height":400},"100sh":{"width":100,"img_url":"http://s2.i1.picplzthumbs.com/upload/img/f2/33/69/f23369cbb88b1215c5640ba780ff7d61c757f1d6_t200s.jpg","height":100},"320rh":{"width":213,"img_url":"http://s2.i1.picplzthumbs.com/upload/img/f2/33/69/f23369cbb88b1215c5640ba780ff7d61c757f1d6_mmed.jpg","height":320}},"caption":"","comment_count":4,"like_count":26,"date":1338058768,"id":11092883},{"view_count":59,"creator":{"username":"gotenba","display_name":"suruga","following_count":2108,"follower_count":6837,"id":232354,"icon":{"url":"http://s1.ui1.picplzthumbs.com/usericons/47/77/4a/47774a177d4ad9a37fd9d292f20df9fbff509b4a_meds.jpg","width":75,"height":75}},"url":"/user/gotenba/pic/1dxkj/","pic_files":{"640r":{"width":640,"img_url":"http://s1.i1.picplzthumbs.com/upload/img/bc/d4/2c/bcd42c5cc25c2c8a2ae007e397a89a7b4c724c5c_wmeg.jpg","height":480},"100sh":{"width":100,"img_url":"http://s1.i1.picplzthumbs.com/upload/img/bc/d4/2c/bcd42c5cc25c2c8a2ae007e397a89a7b4c724c5c_t200s.jpg","height":100},"320rh":{"width":320,"img_url":"http://s1.i1.picplzthumbs.com/upload/img/bc/d4/2c/bcd42c5cc25c2c8a2ae007e397a89a7b4c724c5c_mmed.jpg","height":240}},"caption":"For Kana ^-^v","comment_count":9,"like_count":69,"date":1338038828,"id":11089189},{"view_count":40,"creator":{"username":"gotenba","display_name":"suruga","following_count":2108,"follower_count":6837,"id":232354,"icon":{"url":"http://s1.ui1.picplzthumbs.com/usericons/47/77/4a/47774a177d4ad9a37fd9d292f20df9fbff509b4a_meds.jpg","width":75,"height":75}},"url":"/user/gotenba/pic/1ddw0/","pic_files":{"640r":{"width":640,"img_url":"http://s0.i1.picplzthumbs.com/upload/img/90/74/5c/90745c8f7761bbb741027d3b3a0cf4d60821ff36_wmeg.jpg","height":480},"100sh":{"width":100,"img_url":"http://s0.i1.picplzthumbs.com/upload/img/90/74/5c/90745c8f7761bbb741027d3b3a0cf4d60821ff36_t200s.jpg","height":100},"320rh":{"width":320,"img_url":"http://s0.i1.picplzthumbs.com/upload/img/90/74/5c/90745c8f7761bbb741027d3b3a0cf4d60821ff36_mmed.jpg","height":240}},"caption":"\u4eca\u65e5\u306e\u5bcc\u58eb\u5c71   \u304a\u307e\u3051(^-^)/","comment_count":12,"like_count":66,"date":1338036316,"id":11088882},{"view_count":30,"creator":{"username":"gotenba","display_name":"suruga","following_count":2108,"follower_count":6837,"id":232354,"icon":{"url":"http://s1.ui1.picplzthumbs.com/usericons/47/77/4a/47774a177d4ad9a37fd9d292f20df9fbff509b4a_meds.jpg","width":75,"height":75}},"url":"/user/gotenba/pic/1d8t4/","pic_files":{"640r":{"width":406,"img_url":"http://s1.i1.picplzthumbs.com/upload/img/d1/97/ce/d197ced93dcd684c15822b6f70fd9cbb3201d0da_wmeg.jpg","height":640},"100sh":{"width":100,"img_url":"http://s1.i1.picplzthumbs.com/upload/img/d1/97/ce/d197ced93dcd684c15822b6f70fd9cbb3201d0da_t200s.jpg","height":100},"320rh":{"width":203,"img_url":"http://s1.i1.picplzthumbs.com/upload/img/d1/97/ce/d197ced93dcd684c15822b6f70fd9cbb3201d0da_mmed.jpg","height":320}},"caption":"Good night! \u4eca\u65e5\u3082\u3042\u308a\u304c\u3068\u3046\u3002\u660e\u65e5\u3082\u7686\u304c\u5e73\u548c\u306b\u904e\u3054\u305b\u307e\u3059\u3088\u3046\u306b\u3002\u304a\u3084\u3059\u307f\u306a\u3055\u3044 (^-^)/","comment_count":14,"like_count":57,"date":1338043327,"id":11089975},{"view_count":19,"creator":{"username":"gravity","display_name":"FINDER","following_count":1002,"follower_count":697,"id":221054,"icon":{"url":"http://s0.ui1.picplzthumbs.com/usericons/dc/6d/17/dc6d172a37d04fe94804b712f4c80289c01c1bbd_meds.jpg","width":75,"height":75}},"url":"/user/gravity/pic/1dw1f/","pic_files":{"640r":{"width":425,"img_url":"http://s0.i1.picplzthumbs.com/upload/img/f5/51/fe/f551fe1d4421392f78fd648b6b2953c836ae37f4_wmeg.jpg","height":640},"100sh":{"width":100,"img_url":"http://s0.i1.picplzthumbs.com/upload/img/f5/51/fe/f551fe1d4421392f78fd648b6b2953c836ae37f4_t200s.jpg","height":100},"320rh":{"width":213,"img_url":"http://s0.i1.picplzthumbs.com/upload/img/f5/51/fe/f551fe1d4421392f78fd648b6b2953c836ae37f4_mmed.jpg","height":320}},"caption":"2012\ubd80\uc0b0 \uad6d\uc81c\ubaa8\ud130\uc1fc \uc2a4\ud1a0\ub9ac.","comment_count":0,"like_count":4,"date":1338075971,"id":11096496},{"view_count":16,"creator":{"username":"gravity","display_name":"FINDER","following_count":1002,"follower_count":697,"id":221054,"icon":{"url":"http://s0.ui1.picplzthumbs.com/usericons/dc/6d/17/dc6d172a37d04fe94804b712f4c80289c01c1bbd_meds.jpg","width":75,"height":75}},"url":"/user/gravity/pic/1dwc9/","pic_files":{"640r":{"width":640,"img_url":"http://s1.i1.picplzthumbs.com/upload/img/ea/97/3a/ea973afad4d83f0e31b19b76d8c26f2c009a57b2_wmeg.jpg","height":425},"100sh":{"width":100,"img_url":"http://s1.i1.picplzthumbs.com/upload/img/ea/97/3a/ea973afad4d83f0e31b19b76d8c26f2c009a57b2_t200s.jpg","height":100},"320rh":{"width":320,"img_url":"http://s1.i1.picplzthumbs.com/upload/img/ea/97/3a/ea973afad4d83f0e31b19b76d8c26f2c009a57b2_mmed.jpg","height":213}},"caption":"2012\ubd80\uc0b0 \uad6d\uc81c\ubaa8\ud130\uc1fc \uc2a4\ud1a0\ub9ac.","comment_count":0,"like_count":4,"date":1338076332,"id":11096590},{"view_count":29,"creator":{"username":"gravity","display_name":"FINDER","following_count":1002,"follower_count":697,"id":221054,"icon":{"url":"http://s0.ui1.picplzthumbs.com/usericons/dc/6d/17/dc6d172a37d04fe94804b712f4c80289c01c1bbd_meds.jpg","width":75,"height":75}},"url":"/user/gravity/pic/1dwlt/","pic_files":{"640r":{"width":640,"img_url":"http://s2.i1.picplzthumbs.com/upload/img/36/52/21/3652212acf1e12e11ed451adc2697b19dbe59e15_wmeg.jpg","height":425},"100sh":{"width":100,"img_url":"http://s2.i1.picplzthumbs.com/upload/img/36/52/21/3652212acf1e12e11ed451adc2697b19dbe59e15_t200s.jpg","height":100},"320rh":{"width":320,"img_url":"http://s2.i1.picplzthumbs.com/upload/img/36/52/21/3652212acf1e12e11ed451adc2697b19dbe59e15_mmed.jpg","height":213}},"caption":"2012\ubd80\uc0b0 \uad6d\uc81c\ubaa8\ud130\uc1fc \uc2a4\ud1a0\ub9ac.","comment_count":0,"like_count":4,"date":1338076474,"id":11096615},{"view_count":17,"creator":{"username":"tyroidsystem","display_name":"Mizue Soma","following_count":32,"follower_count":15,"id":1429188,"icon":{"url":"http://s2.ui1.picplzthumbs.com/usericons/c6/34/35/c6343508edb5a84a79323f98c84a02306bd4e5c9_meds.jpg","width":75,"height":75}},"url":"/user/tyroidsystem/pic/1dwlv/","pic_files":{"640r":{"width":640,"img_url":"http://s0.i1.picplzthumbs.com/upload/img/2e/0f/0c/2e0f0c14779ab498969e09722e1ebfe9b8c80dca_wmeg.jpg","height":478},"100sh":{"width":100,"img_url":"http://s0.i1.picplzthumbs.com/upload/img/2e/0f/0c/2e0f0c14779ab498969e09722e1ebfe9b8c80dca_t200s.jpg","height":100},"320rh":{"width":320,"img_url":"http://s0.i1.picplzthumbs.com/upload/img/2e/0f/0c/2e0f0c14779ab498969e09722e1ebfe9b8c80dca_mmed.jpg","height":239}},"caption":"Hello,world! Peony comes!\u30b7\u30e3\u30af\u30e4\u30af\u54b2\u304d\u307e\u3057\u305f\u3002","comment_count":0,"like_count":4,"date":1338076530,"id":11096625},{"view_count":11,"creator":{"username":"tyroidsystem","display_name":"Mizue Soma","following_count":32,"follower_count":15,"id":1429188,"icon":{"url":"http://s2.ui1.picplzthumbs.com/usericons/c6/34/35/c6343508edb5a84a79323f98c84a02306bd4e5c9_meds.jpg","width":75,"height":75}},"url":"/user/tyroidsystem/pic/1dwjx/","pic_files":{"640r":{"width":640,"img_url":"http://s0.i1.picplzthumbs.com/upload/img/d8/4d/6c/d84d6c036ba921e9c6d28a4f8c0a075c6122af01_wmeg.jpg","height":640},"100sh":{"width":100,"img_url":"http://s0.i1.picplzthumbs.com/upload/img/d8/4d/6c/d84d6c036ba921e9c6d28a4f8c0a075c6122af01_t200s.jpg","height":100},"320rh":{"width":320,"img_url":"http://s0.i1.picplzthumbs.com/upload/img/d8/4d/6c/d84d6c036ba921e9c6d28a4f8c0a075c6122af01_mmed.jpg","height":320}},"caption":"","comment_count":0,"like_count":4,"date":1338076764,"id":11096691},{"view_count":6,"creator":{"username":"matildafrisen","display_name":"MatildaFris\u00e9n","following_count":19,"follower_count":498,"id":1235897,"icon":{"url":"http://s2.ui1.picplzthumbs.com/usericons/7f/f7/5e/7ff75e5a59962c91ba3f54aeca0e7a96af6fda13_meds.jpg","width":75,"height":75}},"url":"/user/matildafrisen/pic/1dw7l/","pic_files":{"640r":{"width":270,"img_url":"http://s2.i1.picplzthumbs.com/upload/img/c6/e3/31/c6e331c9298fa08c5f090bbdb9a38bd1096446f1_mmed_00001.jpg","height":320},"100sh":{"width":100,"img_url":"http://s2.i1.picplzthumbs.com/upload/img/c6/e3/31/c6e331c9298fa08c5f090bbdb9a38bd1096446f1_t200s_00001.jpg","height":100},"320rh":{"width":270,"img_url":"http://s2.i1.picplzthumbs.com/upload/img/c6/e3/31/c6e331c9298fa08c5f090bbdb9a38bd1096446f1_mmed_00001.jpg","height":320}},"caption":"We did it!!!!!!!!!!!!!!!!!!!!!!!!","comment_count":0,"like_count":4,"date":1338077500,"id":11096837},{"view_count":20,"creator":{"username":"sacthomas","display_name":"thomas haines","following_count":1783,"follower_count":3770,"id":36387,"icon":{"url":"http://s1.ui1.picplzthumbs.com/usericons/52/27/1c/52271c21339bb3ac0602a9e911e53d27367ee52c_meds.jpg","width":75,"height":75}},"url":"/user/sacthomas/pic/1d4nk/","pic_files":{"640r":{"width":640,"img_url":"http://s0.i1.picplzthumbs.com/upload/img/2c/cf/8d/2ccf8d3f1ec617788125a3c252eb475e18a06cc2_wmeg.jpg","height":480},"100sh":{"width":100,"img_url":"http://s0.i1.picplzthumbs.com/upload/img/2c/cf/8d/2ccf8d3f1ec617788125a3c252eb475e18a06cc2_t200s.jpg","height":100},"320rh":{"width":320,"img_url":"http://s0.i1.picplzthumbs.com/upload/img/2c/cf/8d/2ccf8d3f1ec617788125a3c252eb475e18a06cc2_mmed.jpg","height":240}},"caption":"","comment_count":2,"like_count":23,"date":1338059560,"id":11093049},{"view_count":10,"creator":{"username":"gmarti","display_name":"Gabriel","following_count":268,"follower_count":1128,"id":823791,"icon":{"url":"http://s0.ui1.picplzthumbs.com/usericons/5e/e3/2a/5ee32aaf4aa5f2ba85c268e48e431cfd95bbd911_meds.jpg","width":75,"height":75}},"url":"/user/gmarti/pic/1dmt9/","pic_files":{"640r":{"width":640,"img_url":"http://s1.i1.picplzthumbs.com/upload/img/8d/01/a2/8d01a2870380ff3e9b719e1ee0fc0f682c87dd9b_wmeg.jpg","height":640},"100sh":{"width":100,"img_url":"http://s1.i1.picplzthumbs.com/upload/img/8d/01/a2/8d01a2870380ff3e9b719e1ee0fc0f682c87dd9b_t200s.jpg","height":100},"320rh":{"width":320,"img_url":"http://s1.i1.picplzthumbs.com/upload/img/8d/01/a2/8d01a2870380ff3e9b719e1ee0fc0f682c87dd9b_mmed.jpg","height":320}},"caption":"Tree or face?","comment_count":2,"like_count":18,"date":1338062414,"id":11093560},{"view_count":4,"creator":{"username":"esat","display_name":"Esat","following_count":186,"follower_count":221,"id":1260376,"icon":{"url":"http://s1.ui1.picplzthumbs.com/usericons/ca/1c/d7/ca1cd7adaa37ff68a2cee28c33ddd9871fa8f0f7_meds.jpg","width":75,"height":75}},"url":"/user/esat/pic/1dm94/","pic_files":{"640r":{"width":640,"img_url":"http://s1.i1.picplzthumbs.com/upload/img/78/8f/8e/788f8ef42e855241181366030247f523fd0a9e61_wmeg.jpg","height":480},"100sh":{"width":100,"img_url":"http://s1.i1.picplzthumbs.com/upload/img/78/8f/8e/788f8ef42e855241181366030247f523fd0a9e61_t200s.jpg","height":100},"320rh":{"width":320,"img_url":"http://s1.i1.picplzthumbs.com/upload/img/78/8f/8e/788f8ef42e855241181366030247f523fd0a9e61_mmed.jpg","height":240}},"caption":"","comment_count":2,"like_count":18,"date":1338063144,"id":11093725},{"view_count":2,"creator":{"username":"amanda220808","display_name":"Amanda","following_count":2909,"follower_count":1577,"id":795425,"icon":{"url":"http://s0.ui1.picplzthumbs.com/usericons/99/08/c3/9908c38b3e6cbdd89959827e0b9df0f51764a5ab_meds.jpg","width":75,"height":75}},"url":"/user/amanda220808/pic/1dmq2/","pic_files":{"640r":{"width":640,"img_url":"http://s2.i1.picplzthumbs.com/upload/img/67/78/a4/6778a440e82b0abb92116a1f3dc1be4b03295972_wmeg.jpg","height":640},"100sh":{"width":100,"img_url":"http://s2.i1.picplzthumbs.com/upload/img/67/78/a4/6778a440e82b0abb92116a1f3dc1be4b03295972_t200s.jpg","height":100},"320rh":{"width":320,"img_url":"http://s2.i1.picplzthumbs.com/upload/img/67/78/a4/6778a440e82b0abb92116a1f3dc1be4b03295972_mmed.jpg","height":320}},"caption":"I like this marble cam :)","comment_count":0,"like_count":19,"date":1338063238,"id":11093744},{"city":{"url":"/city/evora-pt/","id":30464,"name":"\u00c9vora, Portugal"},"creator":{"username":"joaogm","display_name":"Joao Marques","following_count":148,"follower_count":340,"id":1227197,"icon":{"url":"http://s2.ui1.picplzthumbs.com/usericons/cb/51/11/cb51113dc9b5be98c827aafa7dd6878c2c878fa1_meds.jpg","width":75,"height":75}},"url":"/user/joaogm/pic/1dmmn/","pic_files":{"640r":{"width":640,"img_url":"http://s0.i1.picplzthumbs.com/upload/img/c2/69/4d/c2694d061eee43c54415f1927278fa6db73857d2_wmeg.jpg","height":640},"100sh":{"width":100,"img_url":"http://s0.i1.picplzthumbs.com/upload/img/c2/69/4d/c2694d061eee43c54415f1927278fa6db73857d2_t200s.jpg","height":100},"320rh":{"width":320,"img_url":"http://s0.i1.picplzthumbs.com/upload/img/c2/69/4d/c2694d061eee43c54415f1927278fa6db73857d2_mmed.jpg","height":320}},"view_count":2,"caption":"2C","comment_count":0,"like_count":18,"place":{"url":"/pics/evora-evora-pt/","id":285174,"name":"\u00c9vora"},"date":1338064980,"id":11094198},{"view_count":2,"creator":{"username":"zubillaga","display_name":"Alex","following_count":406,"follower_count":2622,"id":61,"icon":{"url":"http://s2.ui1.picplzthumbs.com/usericons/13/fc/ba/13fcba51c9f11821b8904a37f0cb5a8083f29c30_meds.jpg","width":75,"height":75}},"url":"/user/zubillaga/pic/1dmrk/","pic_files":{"640r":{"width":480,"img_url":"http://s0.i1.picplzthumbs.com/upload/img/c6/32/42/c6324234c53876ff1220c5f58e4778094e2c5076_wmeg_00001.jpg","height":640},"100sh":{"width":100,"img_url":"http://s0.i1.picplzthumbs.com/upload/img/c6/32/42/c6324234c53876ff1220c5f58e4778094e2c5076_t200s_00001.jpg","height":100},"320rh":{"width":240,"img_url":"http://s0.i1.picplzthumbs.com/upload/img/c6/32/42/c6324234c53876ff1220c5f58e4778094e2c5076_mmed_00001.jpg","height":320}},"caption":"","comment_count":1,"like_count":17,"date":1338061725,"id":11093439},{"city":{"url":"/city/schmalkalden-de/","id":33232,"name":"Schmalkalden, Germany"},"creator":{"username":"larsgebauer","display_name":"Lars Gebauer","following_count":7071,"follower_count":5536,"id":4473,"icon":{"url":"http://s1.ui1.picplzthumbs.com/usericons/17/31/53/173153eb4fb7d9fff573e44fece8a8226a6f3e90_meds.jpg","width":75,"height":75}},"url":"/user/larsgebauer/pic/1dj9s/","pic_files":{"640r":{"width":640,"img_url":"http://s1.i1.picplzthumbs.com/upload/img/8b/2b/6c/8b2b6cae2dd16bd8cdff4df448890b5d2ef60885_wmeg_00001.jpg","height":640},"100sh":{"width":100,"img_url":"http://s1.i1.picplzthumbs.com/upload/img/8b/2b/6c/8b2b6cae2dd16bd8cdff4df448890b5d2ef60885_t200s_00001.jpg","height":100},"320rh":{"width":320,"img_url":"http://s1.i1.picplzthumbs.com/upload/img/8b/2b/6c/8b2b6cae2dd16bd8cdff4df448890b5d2ef60885_mmed_00001.jpg","height":320}},"view_count":43,"caption":"#Church of Niederschmalkalden, #Thuringia, #justnow.","comment_count":1,"like_count":88,"place":{"url":"/pics/bahnhof-niederschmalkalden-wernshausen-thuringen/","id":343521,"name":"Bahnhof Niederschmalkalden"},"date":1338023689,"id":11087428},{"view_count":28,"creator":{"username":"jyunbo","display_name":"\u3058\u3085\u3093\u307c","following_count":591,"follower_count":2097,"id":514190,"icon":{"url":"http://s0.ui1.picplzthumbs.com/usericons/8e/fe/59/8efe5974418a1291673c5fac13769010f3d5d859_meds.jpg","width":75,"height":75}},"url":"/user/jyunbo/pic/1ddbt/","pic_files":{"640r":{"width":640,"img_url":"http://s2.i1.picplzthumbs.com/upload/img/ff/28/fa/ff28fa04fb6656338d310332a68c0c1d5931bc32_wmeg.jpg","height":425},"100sh":{"width":100,"img_url":"http://s2.i1.picplzthumbs.com/upload/img/ff/28/fa/ff28fa04fb6656338d310332a68c0c1d5931bc32_t200s.jpg","height":100},"320rh":{"width":320,"img_url":"http://s2.i1.picplzthumbs.com/upload/img/ff/28/fa/ff28fa04fb6656338d310332a68c0c1d5931bc32_mmed.jpg","height":213}},"caption":"","comment_count":10,"like_count":71,"date":1338030922,"id":11088215},{"view_count":50,"creator":{"username":"ktanakk","display_name":"\u30b1\u30fc\u30bf\u30ca\u30c3\u30af","following_count":970,"follower_count":911,"id":1040360,"icon":{"url":"http://s1.ui1.picplzthumbs.com/usericons/33/de/3c/33de3c57b6a2468cb3ef28110bb5627c7f9a2b36_meds.jpg","width":75,"height":75}},"url":"/user/ktanakk/pic/1dd9f/","pic_files":{"640r":{"width":640,"img_url":"http://s0.i1.picplzthumbs.com/upload/img/03/37/5e/03375e0ac8e8e272e598efed315f708ff802a70a_wmeg_00001.jpg","height":480},"100sh":{"width":100,"img_url":"http://s0.i1.picplzthumbs.com/upload/img/03/37/5e/03375e0ac8e8e272e598efed315f708ff802a70a_t200s_00001.jpg","height":100},"320rh":{"width":320,"img_url":"http://s0.i1.picplzthumbs.com/upload/img/03/37/5e/03375e0ac8e8e272e598efed315f708ff802a70a_mmed_00001.jpg","height":240}},"caption":"flower","comment_count":7,"like_count":70,"date":1338031745,"id":11088306},{"city":{"url":"/city/evora-pt/","id":30464,"name":"\u00c9vora, Portugal"},"creator":{"username":"joaogm","display_name":"Joao Marques","following_count":148,"follower_count":340,"id":1227197,"icon":{"url":"http://s2.ui1.picplzthumbs.com/usericons/cb/51/11/cb51113dc9b5be98c827aafa7dd6878c2c878fa1_meds.jpg","width":75,"height":75}},"url":"/user/joaogm/pic/1d4xb/","pic_files":{"640r":{"width":640,"img_url":"http://s1.i1.picplzthumbs.com/upload/img/6e/de/cd/6edecd185c732e7e86ede31a33403f6b0a395817_wmeg.jpg","height":640},"100sh":{"width":100,"img_url":"http://s1.i1.picplzthumbs.com/upload/img/6e/de/cd/6edecd185c732e7e86ede31a33403f6b0a395817_t200s.jpg","height":100},"320rh":{"width":320,"img_url":"http://s1.i1.picplzthumbs.com/upload/img/6e/de/cd/6edecd185c732e7e86ede31a33403f6b0a395817_mmed.jpg","height":320}},"view_count":6,"caption":"Ground","comment_count":0,"like_count":20,"place":{"url":"/pics/evora-evora-pt/","id":285174,"name":"\u00c9vora"},"date":1338059995,"id":11093137},{"view_count":25,"creator":{"username":"sacthomas","display_name":"thomas haines","following_count":1783,"follower_count":3770,"id":36387,"icon":{"url":"http://s1.ui1.picplzthumbs.com/usericons/52/27/1c/52271c21339bb3ac0602a9e911e53d27367ee52c_meds.jpg","width":75,"height":75}},"url":"/user/sacthomas/pic/1d4n4/","pic_files":{"640r":{"width":480,"img_url":"http://s1.i1.picplzthumbs.com/upload/img/94/40/5d/94405d59bf90e60c8043ba10f4ac690ba17bfcae_wmeg.jpg","height":640},"100sh":{"width":100,"img_url":"http://s1.i1.picplzthumbs.com/upload/img/94/40/5d/94405d59bf90e60c8043ba10f4ac690ba17bfcae_t200s.jpg","height":100},"320rh":{"width":240,"img_url":"http://s1.i1.picplzthumbs.com/upload/img/94/40/5d/94405d59bf90e60c8043ba10f4ac690ba17bfcae_mmed.jpg","height":320}},"caption":"","comment_count":0,"like_count":20,"date":1338059666,"id":11093065},{"view_count":3,"creator":{"username":"gmarti","display_name":"Gabriel","following_count":268,"follower_count":1128,"id":823791,"icon":{"url":"http://s0.ui1.picplzthumbs.com/usericons/5e/e3/2a/5ee32aaf4aa5f2ba85c268e48e431cfd95bbd911_meds.jpg","width":75,"height":75}},"url":"/user/gmarti/pic/1dmth/","pic_files":{"640r":{"width":640,"img_url":"http://s1.i1.picplzthumbs.com/upload/img/70/5c/11/705c11e027eaa4cc480b401ba4b0852340745e38_wmeg.jpg","height":640},"100sh":{"width":100,"img_url":"http://s1.i1.picplzthumbs.com/upload/img/70/5c/11/705c11e027eaa4cc480b401ba4b0852340745e38_t200s.jpg","height":100},"320rh":{"width":320,"img_url":"http://s1.i1.picplzthumbs.com/upload/img/70/5c/11/705c11e027eaa4cc480b401ba4b0852340745e38_mmed.jpg","height":320}},"caption":"Sequoia","comment_count":0,"like_count":15,"date":1338062384,"id":11093554},{"view_count":0,"creator":{"username":"gmarti","display_name":"Gabriel","following_count":268,"follower_count":1128,"id":823791,"icon":{"url":"http://s0.ui1.picplzthumbs.com/usericons/5e/e3/2a/5ee32aaf4aa5f2ba85c268e48e431cfd95bbd911_meds.jpg","width":75,"height":75}},"url":"/user/gmarti/pic/1dmkk/","pic_files":{"640r":{"width":640,"img_url":"http://s0.i1.picplzthumbs.com/upload/img/36/07/c7/3607c7077acf4c20b9c70c666b09799932017bf2_wmeg.jpg","height":640},"100sh":{"width":100,"img_url":"http://s0.i1.picplzthumbs.com/upload/img/36/07/c7/3607c7077acf4c20b9c70c666b09799932017bf2_t200s.jpg","height":100},"320rh":{"width":320,"img_url":"http://s0.i1.picplzthumbs.com/upload/img/36/07/c7/3607c7077acf4c20b9c70c666b09799932017bf2_mmed.jpg","height":320}},"caption":"Sunset at Montseny. Catalonia","comment_count":0,"like_count":15,"date":1338063025,"id":11093679},{"view_count":8,"creator":{"username":"nicola2","display_name":"Nicola Halsall","following_count":439,"follower_count":1153,"id":168429,"icon":{"url":"http://s1.ui1.picplzthumbs.com/usericons/54/20/84/542084bb75803b7773ba152ed16f4da6133fea43_meds.jpg","width":75,"height":75}},"url":"/user/nicola2/pic/1d4n7/","pic_files":{"640r":{"width":640,"img_url":"http://s0.i1.picplzthumbs.com/upload/img/c0/fa/ff/c0faffaa4622c21747a64773871f28947b758db5_wmeg_00001.jpg","height":512},"100sh":{"width":100,"img_url":"http://s0.i1.picplzthumbs.com/upload/img/c0/fa/ff/c0faffaa4622c21747a64773871f28947b758db5_t200s_00001.jpg","height":100},"320rh":{"width":320,"img_url":"http://s0.i1.picplzthumbs.com/upload/img/c0/fa/ff/c0faffaa4622c21747a64773871f28947b758db5_mmed_00001.jpg","height":256}},"caption":"The little goose of Portnahaven, with many thanks to Lars!","comment_count":0,"like_count":19,"date":1338059664,"id":11093064},{"view_count":0,"creator":{"username":"kakerukaze","display_name":"kakeru","following_count":91,"follower_count":66,"id":1493278,"icon":{"url":"http://s2.ui1.picplzthumbs.com/usericons/03/b2/87/03b28774bb360e648773ed0b266069f50250277e_meds.jpg","width":75,"height":75}},"url":"/user/kakerukaze/pic/1dsc4/","pic_files":{"640r":{"width":640,"img_url":"http://s1.i1.picplzthumbs.com/upload/img/e3/4c/a3/e34ca38523375136f026151623de531ca1001790_wmeg_00001.jpg","height":478},"100sh":{"width":100,"img_url":"http://s1.i1.picplzthumbs.com/upload/img/e3/4c/a3/e34ca38523375136f026151623de531ca1001790_t200s_00001.jpg","height":100},"320rh":{"width":320,"img_url":"http://s1.i1.picplzthumbs.com/upload/img/e3/4c/a3/e34ca38523375136f026151623de531ca1001790_mmed_00001.jpg","height":239}},"caption":"\u304a\u306f\u3088\u3046\u3054\u3056\u3044\u307e\u3059(\uff3e\uff70^)\u30ceGood morning!","comment_count":2,"like_count":8,"date":1338071820,"id":11095705},{"view_count":6,"creator":{"username":"winterqueen","display_name":"Saundra","following_count":652,"follower_count":587,"id":343365,"icon":{"url":"http://s1.ui1.picplzthumbs.com/usericons/21/a4/61/21a461c17502286304ae10748a35f3dcb8d37334_meds.jpg","width":75,"height":75}},"url":"/user/winterqueen/pic/1dscn/","pic_files":{"640r":{"width":361,"img_url":"http://s0.i1.picplzthumbs.com/upload/img/25/24/3a/25243a1ecd4d8e71cd3cdce26f07d4a7b3a1e1fd_wmeg.jpg","height":640},"100sh":{"width":100,"img_url":"http://s0.i1.picplzthumbs.com/upload/img/25/24/3a/25243a1ecd4d8e71cd3cdce26f07d4a7b3a1e1fd_t200s.jpg","height":100},"320rh":{"width":180,"img_url":"http://s0.i1.picplzthumbs.com/upload/img/25/24/3a/25243a1ecd4d8e71cd3cdce26f07d4a7b3a1e1fd_mmed.jpg","height":320}},"caption":"Land Of The Free","comment_count":0,"like_count":9,"date":1338071814,"id":11095698},{"city":{"url":"/city/kingston-upon-thames/","id":6029,"name":"Kingston upon Thames"},"creator":{"username":"adamrt","display_name":"Adam Rees-Taylor","following_count":217,"follower_count":349,"id":884490,"icon":{"url":"http://s2.ui1.picplzthumbs.com/usericons/26/e9/40/26e940ae9465a98a39db45816f0cfe561f46ed27_meds.jpg","width":75,"height":75}},"url":"/user/adamrt/pic/1dzdt/","pic_files":{"640r":{"width":640,"img_url":"http://s2.i1.picplzthumbs.com/upload/img/d5/d5/31/d5d5310bd51abd874b4c81d05bbc1aa363dea9f0_wmeg_00001.jpg","height":243},"100sh":{"width":100,"img_url":"http://s2.i1.picplzthumbs.com/upload/img/d5/d5/31/d5d5310bd51abd874b4c81d05bbc1aa363dea9f0_t200s_00001.jpg","height":100},"320rh":{"width":320,"img_url":"http://s2.i1.picplzthumbs.com/upload/img/d5/d5/31/d5d5310bd51abd874b4c81d05bbc1aa363dea9f0_mmed_00001.jpg","height":122}},"view_count":4,"caption":"","comment_count":1,"like_count":10,"date":1338068147,"id":11094905},{"view_count":15,"creator":{"username":"nicola2","display_name":"Nicola Halsall","following_count":439,"follower_count":1153,"id":168429,"icon":{"url":"http://s1.ui1.picplzthumbs.com/usericons/54/20/84/542084bb75803b7773ba152ed16f4da6133fea43_meds.jpg","width":75,"height":75}},"url":"/user/nicola2/pic/1d4w6/","pic_files":{"640r":{"width":640,"img_url":"http://s2.i1.picplzthumbs.com/upload/img/ba/a6/d0/baa6d089f6254277de5843b7f25c36d7a77b4cd9_wmeg_00001.jpg","height":328},"100sh":{"width":100,"img_url":"http://s2.i1.picplzthumbs.com/upload/img/ba/a6/d0/baa6d089f6254277de5843b7f25c36d7a77b4cd9_t200s_00001.jpg","height":100},"320rh":{"width":320,"img_url":"http://s2.i1.picplzthumbs.com/upload/img/ba/a6/d0/baa6d089f6254277de5843b7f25c36d7a77b4cd9_mmed_00001.jpg","height":164}},"caption":"Blue skies in Portnahaven today","comment_count":6,"like_count":18,"date":1338061277,"id":11093372},{"view_count":26,"creator":{"username":"seabird","display_name":"seabird","following_count":612,"follower_count":958,"id":165704,"icon":{"url":"http://s1.ui1.picplzthumbs.com/usericons/bd/85/fd/bd85fdcdbedb57353cd13751b4fb23a74f981dad_meds.jpg","width":75,"height":75}},"url":"/user/seabird/pic/1dw8b/","pic_files":{"640r":{"width":640,"img_url":"http://s1.i1.picplzthumbs.com/upload/img/1e/58/4f/1e584f7919e4cb94f3cc981cde3940d995493ef0_wmeg.jpg","height":640},"100sh":{"width":100,"img_url":"http://s1.i1.picplzthumbs.com/upload/img/1e/58/4f/1e584f7919e4cb94f3cc981cde3940d995493ef0_t200s.jpg","height":100},"320rh":{"width":320,"img_url":"http://s1.i1.picplzthumbs.com/upload/img/1e/58/4f/1e584f7919e4cb94f3cc981cde3940d995493ef0_mmed.jpg","height":320}},"caption":"\u30a2\u30c3\u30d7\u30c7\u30fc\u30c8","comment_count":0,"like_count":3,"date":1338077186,"id":11096767},{"view_count":27,"creator":{"username":"seabird","display_name":"seabird","following_count":612,"follower_count":958,"id":165704,"icon":{"url":"http://s1.ui1.picplzthumbs.com/usericons/bd/85/fd/bd85fdcdbedb57353cd13751b4fb23a74f981dad_meds.jpg","width":75,"height":75}},"url":"/user/seabird/pic/1dw89/","pic_files":{"640r":{"width":427,"img_url":"http://s1.i1.picplzthumbs.com/upload/img/c7/20/6e/c7206e88d33e57f93f94f794f780dcddc4caa7ab_wmeg.jpg","height":640},"100sh":{"width":100,"img_url":"http://s1.i1.picplzthumbs.com/upload/img/c7/20/6e/c7206e88d33e57f93f94f794f780dcddc4caa7ab_t200s.jpg","height":100},"320rh":{"width":213,"img_url":"http://s1.i1.picplzthumbs.com/upload/img/c7/20/6e/c7206e88d33e57f93f94f794f780dcddc4caa7ab_mmed.jpg","height":320}},"caption":"","comment_count":0,"like_count":3,"date":1338077201,"id":11096770},{"view_count":7,"creator":{"username":"itangerine","display_name":"Camille Rose","following_count":236,"follower_count":1026,"id":238994,"icon":{"url":"http://s1.ui1.picplzthumbs.com/usericons/ed/1c/34/ed1c341f40dfe6d5f900c795ba069bab51311ff0_meds.jpg","width":75,"height":75}},"url":"/user/itangerine/pic/1dwxq/","pic_files":{"640r":{"width":480,"img_url":"http://s2.i1.picplzthumbs.com/upload/img/ee/88/bf/ee88bf9c4f9a2984ae1109f3741df2f7446904a4_wmeg_00001.jpg","height":640},"100sh":{"width":100,"img_url":"http://s2.i1.picplzthumbs.com/upload/img/ee/88/bf/ee88bf9c4f9a2984ae1109f3741df2f7446904a4_t200s_00001.jpg","height":100},"320rh":{"width":240,"img_url":"http://s2.i1.picplzthumbs.com/upload/img/ee/88/bf/ee88bf9c4f9a2984ae1109f3741df2f7446904a4_mmed_00001.jpg","height":320}},"caption":"Arabic henna tattoo","comment_count":0,"like_count":4,"date":1338077053,"id":11096741},{"view_count":6,"creator":{"username":"lp0522","display_name":"LP0522","following_count":67,"follower_count":4204,"id":93585,"icon":{"url":"http://s1.ui1.picplzthumbs.com/usericons/97/40/a7/9740a7b20a422a0dd1ebded1ff4b457fab0f0068_meds.jpg","width":75,"height":75}},"url":"/user/lp0522/pic/1dxm6/","pic_files":{"640r":{"width":640,"img_url":"http://s2.i1.picplzthumbs.com/upload/img/b5/36/bb/b536bb77448834703939e45085ed6006922ef431_wmeg.jpg","height":426},"100sh":{"width":100,"img_url":"http://s2.i1.picplzthumbs.com/upload/img/b5/36/bb/b536bb77448834703939e45085ed6006922ef431_t200s.jpg","height":100},"320rh":{"width":320,"img_url":"http://s2.i1.picplzthumbs.com/upload/img/b5/36/bb/b536bb77448834703939e45085ed6006922ef431_mmed.jpg","height":213}},"caption":"","comment_count":3,"like_count":42,"date":1338041801,"id":11089682},{"view_count":4,"creator":{"username":"evazgz","display_name":"Eva G. ","following_count":582,"follower_count":878,"id":276211,"icon":{"url":"http://s2.ui1.picplzthumbs.com/usericons/11/38/41/113841a2f7884f3dd3b4acc38682e36fc089d8c1_meds.jpg","width":75,"height":75}},"url":"/user/evazgz/pic/1d4ct/","pic_files":{"640r":{"width":640,"img_url":"http://s2.i1.picplzthumbs.com/upload/img/30/bf/c7/30bfc7584d7b36a74bd294cb400fe747d2517f62_wmeg.jpg","height":478},"100sh":{"width":100,"img_url":"http://s2.i1.picplzthumbs.com/upload/img/30/bf/c7/30bfc7584d7b36a74bd294cb400fe747d2517f62_t200s.jpg","height":100},"320rh":{"width":320,"img_url":"http://s2.i1.picplzthumbs.com/upload/img/30/bf/c7/30bfc7584d7b36a74bd294cb400fe747d2517f62_mmed.jpg","height":239}},"caption":"Atardeceres","comment_count":0,"like_count":17,"date":1338058446,"id":11092985},{"view_count":12,"creator":{"username":"nicola2","display_name":"Nicola Halsall","following_count":439,"follower_count":1153,"id":168429,"icon":{"url":"http://s1.ui1.picplzthumbs.com/usericons/54/20/84/542084bb75803b7773ba152ed16f4da6133fea43_meds.jpg","width":75,"height":75}},"url":"/user/nicola2/pic/1d4nf/","pic_files":{"640r":{"width":640,"img_url":"http://s0.i1.picplzthumbs.com/upload/img/4e/08/a0/4e08a0b4d342edea555bcba3b90cdc3c788a00ed_wmeg_00001.jpg","height":319},"100sh":{"width":100,"img_url":"http://s0.i1.picplzthumbs.com/upload/img/4e/08/a0/4e08a0b4d342edea555bcba3b90cdc3c788a00ed_t200s_00001.jpg","height":100},"320rh":{"width":320,"img_url":"http://s0.i1.picplzthumbs.com/upload/img/4e/08/a0/4e08a0b4d342edea555bcba3b90cdc3c788a00ed_mmed_00001.jpg","height":160}},"caption":"Sunset over Claddach","comment_count":4,"like_count":17,"date":1338059560,"id":11093046},{"view_count":7,"creator":{"username":"anmetalna","display_name":"Nice Metal WonBin 5BBA ","following_count":2036,"follower_count":2061,"id":1119473,"icon":{"url":"http://s1.ui1.picplzthumbs.com/usericons/a7/4f/6f/a74f6f835be4d7b16e2ec6977f1650b8bdd83d51_meds.jpg","width":75,"height":75}},"url":"/user/anmetalna/pic/1dxfm/","pic_files":{"640r":{"width":640,"img_url":"http://s2.i1.picplzthumbs.com/upload/img/39/c8/84/39c8848b1bc5d9b30bc8de296f9c9649764fc5dc_wmeg.jpg","height":640},"100sh":{"width":100,"img_url":"http://s2.i1.picplzthumbs.com/upload/img/39/c8/84/39c8848b1bc5d9b30bc8de296f9c9649764fc5dc_t200s.jpg","height":100},"320rh":{"width":320,"img_url":"http://s2.i1.picplzthumbs.com/upload/img/39/c8/84/39c8848b1bc5d9b30bc8de296f9c9649764fc5dc_mmed.jpg","height":320}},"caption":"","comment_count":0,"like_count":46,"date":1338038299,"id":11089106},{"view_count":21,"creator":{"username":"999dangermouse","display_name":"Marie M","following_count":33,"follower_count":156,"id":928463,"icon":{"url":"http://s2.ui1.picplzthumbs.com/usericons/9d/99/99/9d99998f65bf78da1352787da195d412fb6cc827_meds.jpg","width":75,"height":75}},"url":"/user/999dangermouse/pic/1dz39/","pic_files":{"640r":{"width":478,"img_url":"http://s1.i1.picplzthumbs.com/upload/img/f4/e9/dc/f4e9dc9db009b90049dd422ae1d072de8aa0a7b6_wmeg.jpg","height":640},"100sh":{"width":100,"img_url":"http://s1.i1.picplzthumbs.com/upload/img/f4/e9/dc/f4e9dc9db009b90049dd422ae1d072de8aa0a7b6_t200s.jpg","height":100},"320rh":{"width":239,"img_url":"http://s1.i1.picplzthumbs.com/upload/img/f4/e9/dc/f4e9dc9db009b90049dd422ae1d072de8aa0a7b6_mmed.jpg","height":320}},"caption":"Loving this beautiful & the beauty where I live. Take care everyone xxxx","comment_count":4,"like_count":10,"date":1338066486,"id":11094550},{"view_count":9,"creator":{"username":"winterqueen","display_name":"Saundra","following_count":652,"follower_count":587,"id":343365,"icon":{"url":"http://s1.ui1.picplzthumbs.com/usericons/21/a4/61/21a461c17502286304ae10748a35f3dcb8d37334_meds.jpg","width":75,"height":75}},"url":"/user/winterqueen/pic/1dsl8/","pic_files":{"640r":{"width":361,"img_url":"http://s1.i1.picplzthumbs.com/upload/img/9f/aa/22/9faa22c16547e06fe7f72b39177457919dec3b72_wmeg.jpg","height":640},"100sh":{"width":100,"img_url":"http://s1.i1.picplzthumbs.com/upload/img/9f/aa/22/9faa22c16547e06fe7f72b39177457919dec3b72_t200s.jpg","height":100},"320rh":{"width":180,"img_url":"http://s1.i1.picplzthumbs.com/upload/img/9f/aa/22/9faa22c16547e06fe7f72b39177457919dec3b72_mmed.jpg","height":320}},"caption":"Peek a boo","comment_count":0,"like_count":7,"date":1338071990,"id":11095732},{"city":{"url":"/city/evora-pt/","id":30464,"name":"\u00c9vora, Portugal"},"creator":{"username":"joaogm","display_name":"Joao Marques","following_count":148,"follower_count":340,"id":1227197,"icon":{"url":"http://s2.ui1.picplzthumbs.com/usericons/cb/51/11/cb51113dc9b5be98c827aafa7dd6878c2c878fa1_meds.jpg","width":75,"height":75}},"url":"/user/joaogm/pic/1d4xx/","pic_files":{"640r":{"width":640,"img_url":"http://s0.i1.picplzthumbs.com/upload/img/c4/c2/c3/c4c2c32df18421b191a1d24f181c79f0f819169e_wmeg.jpg","height":640},"100sh":{"width":100,"img_url":"http://s0.i1.picplzthumbs.com/upload/img/c4/c2/c3/c4c2c32df18421b191a1d24f181c79f0f819169e_t200s.jpg","height":100},"320rh":{"width":320,"img_url":"http://s0.i1.picplzthumbs.com/upload/img/c4/c2/c3/c4c2c32df18421b191a1d24f181c79f0f819169e_mmed.jpg","height":320}},"view_count":3,"caption":"S\u00e9(u)","comment_count":0,"like_count":16,"place":{"url":"/pics/se-de-evora-evora-pt/","id":343626,"name":"S\u00e9 De \u00c9vora"},"date":1338060076,"id":11093151},{"view_count":4,"creator":{"username":"martinisantos","display_name":"martini","following_count":543,"follower_count":2070,"id":405085,"icon":{"url":"http://s0.ui1.picplzthumbs.com/usericons/f9/e1/45/f9e145160d7c9a1da11e9157de63f58b0d9ecd56_meds.jpg","width":75,"height":75}},"url":"/user/martinisantos/pic/1d5v1/","pic_files":{"640r":{"width":427,"img_url":"http://s1.i1.picplzthumbs.com/upload/img/9d/cf/94/9dcf945842ff2380603ef4c260b9141d885445a5_wmeg.jpg","height":640},"100sh":{"width":100,"img_url":"http://s1.i1.picplzthumbs.com/upload/img/9d/cf/94/9dcf945842ff2380603ef4c260b9141d885445a5_t200s.jpg","height":100},"320rh":{"width":213,"img_url":"http://s1.i1.picplzthumbs.com/upload/img/9d/cf/94/9dcf945842ff2380603ef4c260b9141d885445a5_mmed.jpg","height":320}},"caption":"Ciccio","comment_count":1,"like_count":28,"date":1338049821,"id":11091163},{"view_count":3,"creator":{"username":"j1ichikawa","display_name":"Junichi ICHIKAWA\uff0f\u3062\u3085\u3093","following_count":573,"follower_count":573,"id":94647,"icon":{"url":"http://s0.ui1.picplzthumbs.com/usericons/28/be/c6/28bec6369f44deadb4e1d0bc0fea030b153d5666_meds.jpg","width":75,"height":75}},"url":"/user/j1ichikawa/pic/1dm6c/","pic_files":{"640r":{"width":640,"img_url":"http://s1.i1.picplzthumbs.com/upload/img/2c/78/f7/2c78f7d789fc9de27900a7c6af01b6902eecd433_wmeg.jpg","height":478},"100sh":{"width":100,"img_url":"http://s1.i1.picplzthumbs.com/upload/img/2c/78/f7/2c78f7d789fc9de27900a7c6af01b6902eecd433_t200s.jpg","height":100},"320rh":{"width":320,"img_url":"http://s1.i1.picplzthumbs.com/upload/img/2c/78/f7/2c78f7d789fc9de27900a7c6af01b6902eecd433_mmed.jpg","height":239}},"caption":"Sunrise","comment_count":2,"like_count":12,"date":1338061921,"id":11093476},{"view_count":4,"creator":{"username":"crepuscolo7","display_name":"Arata","following_count":70,"follower_count":64,"id":1420632,"icon":{"url":"http://s1.ui1.picplzthumbs.com/usericons/a6/f3/48/a6f3486ff85d9c5ff736ad05d21f28f1c259dd94_meds.jpg","width":75,"height":75}},"url":"/user/crepuscolo7/pic/1dmdk/","pic_files":{"640r":{"width":640,"img_url":"http://s0.i1.picplzthumbs.com/upload/img/e7/57/47/e7574730a8bbb760357ab82cc2cfee1cbce8e903_wmeg.jpg","height":480},"100sh":{"width":100,"img_url":"http://s0.i1.picplzthumbs.com/upload/img/e7/57/47/e7574730a8bbb760357ab82cc2cfee1cbce8e903_t200s.jpg","height":100},"320rh":{"width":320,"img_url":"http://s0.i1.picplzthumbs.com/upload/img/e7/57/47/e7574730a8bbb760357ab82cc2cfee1cbce8e903_mmed.jpg","height":240}},"caption":"","comment_count":0,"like_count":12,"date":1338064335,"id":11094009},{"view_count":17,"creator":{"username":"999dangermouse","display_name":"Marie M","following_count":33,"follower_count":156,"id":928463,"icon":{"url":"http://s2.ui1.picplzthumbs.com/usericons/9d/99/99/9d99998f65bf78da1352787da195d412fb6cc827_meds.jpg","width":75,"height":75}},"url":"/user/999dangermouse/pic/1dzb8/","pic_files":{"640r":{"width":640,"img_url":"http://s1.i1.picplzthumbs.com/upload/img/3f/e9/6d/3fe96dd91d5f45a9697d37e4196f6a5e51d4c617_wmeg.jpg","height":478},"100sh":{"width":100,"img_url":"http://s1.i1.picplzthumbs.com/upload/img/3f/e9/6d/3fe96dd91d5f45a9697d37e4196f6a5e51d4c617_t200s.jpg","height":100},"320rh":{"width":320,"img_url":"http://s1.i1.picplzthumbs.com/upload/img/3f/e9/6d/3fe96dd91d5f45a9697d37e4196f6a5e51d4c617_mmed.jpg","height":239}},"caption":"Again I thought about modifying but no need! Just beauty at its best","comment_count":0,"like_count":9,"date":1338066430,"id":11094532},{"view_count":14,"creator":{"username":"999dangermouse","display_name":"Marie M","following_count":33,"follower_count":156,"id":928463,"icon":{"url":"http://s2.ui1.picplzthumbs.com/usericons/9d/99/99/9d99998f65bf78da1352787da195d412fb6cc827_meds.jpg","width":75,"height":75}},"url":"/user/999dangermouse/pic/1dz3g/","pic_files":{"640r":{"width":478,"img_url":"http://s0.i1.picplzthumbs.com/upload/img/bf/40/88/bf4088fc7803804a9c3411a471d71d9b06369c97_wmeg.jpg","height":640},"100sh":{"width":100,"img_url":"http://s0.i1.picplzthumbs.com/upload/img/bf/40/88/bf4088fc7803804a9c3411a471d71d9b06369c97_t200s.jpg","height":100},"320rh":{"width":239,"img_url":"http://s0.i1.picplzthumbs.com/upload/img/bf/40/88/bf4088fc7803804a9c3411a471d71d9b06369c97_mmed.jpg","height":320}},"caption":"Loved this log! Lol","comment_count":0,"like_count":9,"date":1338066451,"id":11094543},{"view_count":2,"creator":{"username":"amanda220808","display_name":"Amanda","following_count":2909,"follower_count":1577,"id":795425,"icon":{"url":"http://s0.ui1.picplzthumbs.com/usericons/99/08/c3/9908c38b3e6cbdd89959827e0b9df0f51764a5ab_meds.jpg","width":75,"height":75}},"url":"/user/amanda220808/pic/1d4cz/","pic_files":{"640r":{"width":640,"img_url":"http://s0.i1.picplzthumbs.com/upload/img/f5/fa/a7/f5faa749cdf341fd7a4126481cfa0562d10dbc92_wmeg.jpg","height":640},"100sh":{"width":100,"img_url":"http://s0.i1.picplzthumbs.com/upload/img/f5/fa/a7/f5faa749cdf341fd7a4126481cfa0562d10dbc92_t200s.jpg","height":100},"320rh":{"width":320,"img_url":"http://s0.i1.picplzthumbs.com/upload/img/f5/fa/a7/f5faa749cdf341fd7a4126481cfa0562d10dbc92_mmed.jpg","height":320}},"caption":"Texas Rangers","comment_count":2,"like_count":18,"date":1338059359,"id":11093007},{"view_count":17,"creator":{"username":"sacthomas","display_name":"thomas haines","following_count":1783,"follower_count":3770,"id":36387,"icon":{"url":"http://s1.ui1.picplzthumbs.com/usericons/52/27/1c/52271c21339bb3ac0602a9e911e53d27367ee52c_meds.jpg","width":75,"height":75}},"url":"/user/sacthomas/pic/1d4ls/","pic_files":{"640r":{"width":480,"img_url":"http://s1.i1.picplzthumbs.com/upload/img/39/28/a6/3928a6a3187eaf1a1cdfda2cf001ece23f5f4512_wmeg.jpg","height":640},"100sh":{"width":100,"img_url":"http://s1.i1.picplzthumbs.com/upload/img/39/28/a6/3928a6a3187eaf1a1cdfda2cf001ece23f5f4512_t200s.jpg","height":100},"320rh":{"width":240,"img_url":"http://s1.i1.picplzthumbs.com/upload/img/39/28/a6/3928a6a3187eaf1a1cdfda2cf001ece23f5f4512_mmed.jpg","height":320}},"caption":"#wacky #weather","comment_count":1,"like_count":15,"place":{"url":"/pics/grass-valley-ca-grass-valley-ca/","id":343621,"name":"Grass Valley, Ca"},"date":1338059526,"id":11093038},{"view_count":10,"creator":{"username":"skybluesky","display_name":"sorato:","following_count":18,"follower_count":128,"id":1477975,"icon":{"url":"http://s0.ui1.picplzthumbs.com/usericons/7f/e6/9c/7fe69cca54076ff6a298e42be8608d486cc79baa_meds.jpg","width":75,"height":75}},"url":"/user/skybluesky/pic/1dxl4/","pic_files":{"640r":{"width":640,"img_url":"http://s1.i1.picplzthumbs.com/upload/img/f5/76/de/f576dea2cbf3ccefebeff8ada11ef49614cd5a2f_wmeg_00001.jpg","height":482},"100sh":{"width":100,"img_url":"http://s1.i1.picplzthumbs.com/upload/img/f5/76/de/f576dea2cbf3ccefebeff8ada11ef49614cd5a2f_t200s_00001.jpg","height":100},"320rh":{"width":320,"img_url":"http://s1.i1.picplzthumbs.com/upload/img/f5/76/de/f576dea2cbf3ccefebeff8ada11ef49614cd5a2f_mmed_00001.jpg","height":241}},"caption":"\u300c\u7a7a\u306e\u5b50\u305f\u3061\u300d\u306e\u82b1 \u2160","comment_count":4,"like_count":35,"date":1338040458,"id":11089435},{"view_count":21,"creator":{"username":"26262626","display_name":"\u98a8\u5442","following_count":97,"follower_count":603,"id":757683,"icon":{"url":"http://s2.ui1.picplzthumbs.com/usericons/2c/a0/21/2ca021f1ca25c371996d4f55b434771f5adb144a_meds.jpg","width":75,"height":75}},"url":"/user/26262626/pic/1d4gl/","pic_files":{"640r":{"width":640,"img_url":"http://s2.i1.picplzthumbs.com/upload/img/73/fb/86/73fb864ab89df35ba6fccc6d8573d9352b85cd2c_wmeg.jpg","height":384},"100sh":{"width":100,"img_url":"http://s2.i1.picplzthumbs.com/upload/img/73/fb/86/73fb864ab89df35ba6fccc6d8573d9352b85cd2c_t200s.jpg","height":100},"320rh":{"width":320,"img_url":"http://s2.i1.picplzthumbs.com/upload/img/73/fb/86/73fb864ab89df35ba6fccc6d8573d9352b85cd2c_mmed.jpg","height":192}},"caption":"\u9154\u751f\u5922\u6b7b","comment_count":0,"like_count":18,"date":1338057410,"id":11092607}]}}